Workbook

Sheet Summary
B4: st 1 | C4: ='Income - Stage 1'!D24 -> 462500 | D4: =C4/$C$17 -> 0.31127962
B5: st 2 | C5: ='Income - Stage 1'!D127 -> 475000 | D5: =C5/$C$17 -> 0.31969258
B6: st 3 | D6: =C6/$C$17 -> 0
B7: aust | C7: ='Domestic Holidays'!D29 -> 115568.24 | D7: =C7/$C$17 -> 0.0777817
B8: int | C8: ='International Holidays'!D29 -> 142534.16 | D8: =C8/$C$17 -> 0.095930763
D9: =C9/$C$17 -> 0
D10: =C10/$C$17 -> 0
B11: cp1 | C11: ='Car - P1'!D29 -> 112500 | D11: =C11/$C$17 -> 0.075716664
B12: cp2 | C12: ='Car P2'!D29 -> 96200 | D12: =C12/$C$17 -> 0.06474616
B13: car | C13: =Carvan!D50 -> 81500 | D13: =C13/$C$17 -> 0.054852516
C17: =SUM(C4:C15) -> 1485802.4 | D17: =SUM(D4:D15) -> 1

Sheet Portflio Assuptions

Sheet Income - Stage 1
B2: Stage 1
B3: Calander Year at Stage | C3: 2026
B4: Start year | C4: 1
B5: Stage length | C5: 5
B6: Finish Year | C6: =C3+C5 -> 2031
B7: Partner 1 age | C7: 65
B8: Partner 2 age | C8: 62
B9: Tax Rate (%) | C9: 0.15
B10: Fees % | C10: 0.011
B11: Inflation | C11: 0.03
B13: Portfolio | C13: Conservative | D13: "- this is a pull down menue that automatically fills in the Income % and Growth %"
B14: Portfolio Attributes
B15: income return (%) | C15: 0.045
B16: Growth (%) | C16: 0.005
B18: Calander Year | D18: =C3 -> 2026 | E18: =D18+1 -> 2027 | F18: =E18+1 -> 2028 | G18: =F18+1 -> 2029 | H18: =G18+1 -> 2030 | I18: =H18+1 -> 2031 | J18: =I18+1 -> 2032 | K18: =J18+1 -> 2033 | L18: =K18+1 -> 2034 | M18: =L18+1 -> 2035
B19: Year | D19: 0 | E19: =D19+1 -> 1 | F19: =E19+1 -> 2 | G19: =F19+1 -> 3 | H19: =G19+1 -> 4 | I19: =H19+1 -> 5 | J19: =I19+1 -> 6 | K19: =J19+1 -> 7 | L19: =K19+1 -> 8 | M19: =L19+1 -> 9
B20: Partner 1 age | D20: =C7 -> 65 | E20: =D20+1 -> 66 | F20: =E20+1 -> 67 | G20: =F20+1 -> 68 | H20: =G20+1 -> 69 | I20: =H20+1 -> 70 | J20: =I20+1 -> 71 | K20: =J20+1 -> 72 | L20: =K20+1 -> 73 | M20: =L20+1 -> 74
B21: Partner 2 age | D21: =C8 -> 62 | E21: =D21+1 -> 63 | F21: =E21+1 -> 64 | G21: =F21+1 -> 65 | H21: =G21+1 -> 66 | I21: =H21+1 -> 67 | J21: =I21+1 -> 68 | K21: =J21+1 -> 69 | L21: =K21+1 -> 70 | M21: =L21+1 -> 71
B24: open balance | D24: 462500 | E24: =D34-D42 -> 397415.62 | F24: =E34-E42 -> 327832.28 | G24: =F34-F42 -> 253532.87 | H24: =G34-G42 -> 174291.14 | I24: =H34-H42 -> 89871.33 | J24: =I34-I42 -> 27.754015 | K24: =J34-J42 -> 28.954376 | L24: =K34-K42 -> 30.206653 | M24: =L34-L42 -> 31.513091
B25: income return (%) | D25: =C15 -> 0.045 | E25: =D25 -> 0.045 | F25: =E25 -> 0.045 | G25: =F25 -> 0.045 | H25: =G25 -> 0.045 | I25: =H25 -> 0.045 | J25: =I25 -> 0.045 | K25: =J25 -> 0.045 | L25: =K25 -> 0.045 | M25: =L25 -> 0.045
B26: income return ($) | D26: =D24*D25 -> 20812.5 | E26: =E24*E25 -> 17883.703 | F26: =F24*F25 -> 14752.453 | G26: =G24*G25 -> 11408.979 | H26: =H24*H25 -> 7843.1015 | I26: =I24*I25 -> 4044.2098 | J26: =J24*J25 -> 1.2489307 | K26: =K24*K25 -> 1.3029469 | ... M26: =M24*M25 -> 1.4180891
B27: Tax Rate (%) | D27: =C9 -> 0.15 | E27: =D27 -> 0.15 | F27: =E27 -> 0.15 | G27: =F27 -> 0.15 | H27: =G27 -> 0.15 | I27: =H27 -> 0.15 | J27: =I27 -> 0.15 | K27: =J27 -> 0.15 | L27: =K27 -> 0.15 | M27: =L27 -> 0.15
B28: Tax Rate ($) | D28: =IF((D26*D27)<0,0,(D26*D27)) -> 3121.875 | E28: =IF((E26*E27)<0,0,(E26*E27)) -> 2682.5555 | F28: =IF((F26*F27)<0,0,(F26*F27)) -> 2212.8679 | G28: =IF((G26*G27)<0,0,(G26*G27)) -> 1711.3469 | H28: =IF((H26*H27)<0,0,(H26*H27)) -> 1176.4652 | I28: =IF((I26*I27)<0,0,(I26*I27)) -> 606.63147 | J28: =IF((J26*J27)<0,0,(J26*J27)) -> 0.1873396 | K28: =IF((K26*K27)<0,0,(K26*K27)) -> 0.19544204 | ... M28: =IF((M26*M27)<0,0,(M26*M27)) -> 0.21271336 | V28: =SUM(D28:N28) -> 11512.541
B29: Income after tax | D29: =IF((D26-D28)<0,0,(D26-D28)) -> 17690.625 | E29: =IF((E26-E28)<0,0,(E26-E28)) -> 15201.148 | F29: =IF((F26-F28)<0,0,(F26-F28)) -> 12539.585 | G29: =IF((G26-G28)<0,0,(G26-G28)) -> 9697.6323 | H29: =IF((H26-H28)<0,0,(H26-H28)) -> 6666.6363 | I29: =IF((I26-I28)<0,0,(I26-I28)) -> 3437.5784 | J29: =IF((J26-J28)<0,0,(J26-J28)) -> 1.0615911 | K29: =IF((K26-K28)<0,0,(K26-K28)) -> 1.1075049 | ... M29: =IF((M26-M28)<0,0,(M26-M28)) -> 1.2053757 | V29: =SUM(D29:N29) -> 65237.734
B31: Growth (%) | D31: =C16 -> 0.005 | E31: =D31 -> 0.005 | F31: =E31 -> 0.005 | G31: =F31 -> 0.005 | H31: =G31 -> 0.005 | I31: =H31 -> 0.005 | J31: =I31 -> 0.005 | K31: =J31 -> 0.005 | L31: =K31 -> 0.005 | M31: =L31 -> 0.005
B32: Growth ($) | D32: =IF((D31*D24)<0,0,(D31*D24)) -> 2312.5 | E32: =IF((E31*E24)<0,0,(E31*E24)) -> 1987.0781 | F32: =IF((F31*F24)<0,0,(F31*F24)) -> 1639.1614 | G32: =IF((G31*G24)<0,0,(G31*G24)) -> 1267.6643 | H32: =IF((H31*H24)<0,0,(H31*H24)) -> 871.45572 | I32: =IF((I31*I24)<0,0,(I31*I24)) -> 449.35665 | J32: =IF((J31*J24)<0,0,(J31*J24)) -> 0.13877008 | K32: =IF((K31*K24)<0,0,(K31*K24)) -> 0.14477188 | ... M32: =IF((M31*M24)<0,0,(M31*M24)) -> 0.15756545 | V32: =SUM(D32:M32) -> 8527.8084
B34: Closing Balance | D34: =D24+D29+D32 -> 482503.12 | E34: =E24+E29+E32 -> 414603.85 | F34: =F24+F29+F32 -> 342011.02 | G34: =G24+G29+G32 -> 264498.17 | H34: =H24+H29+H32 -> 181829.24 | I34: =I24+I29+I32 -> 93758.265 | J34: =J24+J29+J32 -> 28.954376 | K34: =K24+K29+K32 -> 30.206653 | ... M34: =M24+M29+M32 -> 32.876032
B36: income needed ex fees | D36: 80000 | E36: =D36*(1+D37) -> 82400 | F36: =E36*(1+E37) -> 84872 | G36: =F36*(1+F37) -> 87418.16 | H36: =G36*(1+G37) -> 90040.705 | I36: =H36*(1+H37) -> 92741.926 | J36: =I36*(1+I37) -> 95524.184 | K36: =J36*(1+J37) -> 98389.909 | L36: =K36*(1+K37) -> 101341.61 | M36: =L36*(1+L37) -> 104381.85
B37: Inflation assumed | D37: =C11 -> 0.03 | E37: =D37 -> 0.03 | F37: =E37 -> 0.03 | G37: =F37 -> 0.03 | H37: =G37 -> 0.03 | I37: =H37 -> 0.03 | J37: =I37 -> 0.03 | K37: =J37 -> 0.03 | L37: =K37 -> 0.03 | M37: =L37 -> 0.03
B39: Fees (%) | D39: =C10 -> 0.011 | E39: =D39 -> 0.011 | F39: =E39 -> 0.011 | G39: =F39 -> 0.011 | H39: =G39 -> 0.011 | I39: =H39 -> 0.011 | J39: =I39 -> 0.011 | K39: =J39 -> 0.011 | L39: =K39 -> 0.011 | M39: =L39 -> 0.011
B40: Fees ($) | D40: =IF((D39*D24)<0,0,(D39*D24)) -> 5087.5 | E40: =IF((E39*E24)<0,0,(E39*E24)) -> 4371.5719 | F40: =IF((F39*F24)<0,0,(F39*F24)) -> 3606.1551 | G40: =IF((G39*G24)<0,0,(G39*G24)) -> 2788.8616 | H40: =IF((H39*H24)<0,0,(H39*H24)) -> 1917.2026 | I40: =IF((I39*I24)<0,0,(I39*I24)) -> 988.58463 | J40: =IF((J39*J24)<0,0,(J39*J24)) -> 0.30529417 | K40: =IF((K39*K24)<0,0,(K39*K24)) -> 0.31849814 | ... M40: =IF((M39*M24)<0,0,(M39*M24)) -> 0.346644 | V40: =SUM(D40:N40) -> 18761.178 | W40: =V40/V42 -> 0.034987011
B42: income needed inclusive of fees | D42: =IF(D19<=$C$5,(D36+D40),0) -> 85087.5 | E42: =IF(E19<=$C$5,(E36+E40),0) -> 86771.572 | F42: =IF(F19<=$C$5,(F36+F40),0) -> 88478.155 | G42: =IF(G19<=$C$5,(G36+G40),0) -> 90207.022 | H42: =IF(H19<=$C$5,(H36+H40),0) -> 91957.907 | I42: =IF(I19<=$C$5,(I36+I40),0) -> 93730.511 | J42: =IF(J19<=$C$5,(J36+J40),0) -> 0 | K42: =IF(K19<=$C$5,(K36+K40),0) -> 0 | ... M42: =IF(M19<=$C$5,(M36+M40),0) -> 0 | V42: =SUM(D42:N42) -> 536232.67
B44: Finial Closing balance | D44: =D34-D36 -> 402503.12 | E44: =E34-E36 -> 332203.85 | F44: =F34-F36 -> 257139.02 | G44: =G34-G36 -> 177080.01 | H44: =H34-H36 -> 91788.532 | I44: =I34-I36 -> 1016.3386 | J44: =J34-J36 -> -95495.229 | K44: =K34-K36 -> -98359.703 | ... M44: =M34-M36 -> -104348.98
B47: Stage 2
B48: Calander Year at Stage | C48: =(C3+C5)+1 -> 2032
B49: Start year | C49: =C48-C3 -> 6
B50: Stage length | C50: 10
B51: Finish Year | C51: =C48+C50 -> 2042
B52: The year that needs to be iqual to $0 is | C52: =C51+1 -> 2043
B54: Partner 1 age at start of Stage | C54: =C7+C5 -> 70
B55: Partner 1 age at END of Stage | C55: =C54+C50 -> 80
B57: Partner 2 age at stage of stage | C57: =C8+C5 -> 67
B58: Partner 2 age at END of Stage | C58: =C57+C50 -> 77
B60: Tax Rate (%) | C60: 0.15
B61: Fees % | C61: 0.011
B62: Inflation | C62: 0.03
B64: Portfolio | C64: Balanced | D64: "- this is a pull down menue that automatically fills in the Income % and Growth %"
B65: Portfolio Attributes
B66: income return (%) | C66: 0.035
B67: Growth (%) | C67: 0.045
B69: Calander Year | D69: =C48 -> 2032 | E69: =D69+1 -> 2033 | F69: =E69+1 -> 2034 | G69: =F69+1 -> 2035 | H69: =G69+1 -> 2036 | I69: =H69+1 -> 2037 | J69: =I69+1 -> 2038 | K69: =J69+1 -> 2039 | L69: =K69+1 -> 2040 | ... T69: =S69+1 -> 2048
B70: Year | D70: =C49 -> 6 | E70: =D70+1 -> 7 | F70: =E70+1 -> 8 | G70: =F70+1 -> 9 | H70: =G70+1 -> 10 | I70: =H70+1 -> 11 | J70: =I70+1 -> 12 | K70: =J70+1 -> 13 | L70: =K70+1 -> 14 | ... T70: =S70+1 -> 22
B71: Partner 1 age | D71: =C54 -> 70 | E71: =D71+1 -> 71 | F71: =E71+1 -> 72 | G71: =F71+1 -> 73 | H71: =G71+1 -> 74 | I71: =H71+1 -> 75 | J71: =I71+1 -> 76 | K71: =J71+1 -> 77 | L71: =K71+1 -> 78 | ... T71: =S71+1 -> 86
B72: Partner 2 age | D72: =C57 -> 67 | E72: =D72+1 -> 68 | F72: =E72+1 -> 69 | G72: =F72+1 -> 70 | H72: =G72+1 -> 71 | I72: =H72+1 -> 72 | J72: =I72+1 -> 73 | K72: =J72+1 -> 74 | L72: =K72+1 -> 75 | ... T72: =S72+1 -> 83
B75: open balance | D75: 707800 | E75: =D85-D93 -> 672922.25 | F75: =E85-E93 -> 633421.04 | G75: =F85-F93 -> 588929.63 | H75: =G85-G93 -> 539055.74 | I75: =H85-H93 -> 483379.84 | J75: =I85-I93 -> 421453.38 | K75: =J85-J93 -> 352796.85 | L75: =K85-K93 -> 276897.74 | ... T75: =S85-S93 -> 112.03196
B76: income return (%) | D76: =C66 -> 0.035 | E76: =D76 -> 0.035 | F76: =E76 -> 0.035 | G76: =F76 -> 0.035 | H76: =G76 -> 0.035 | I76: =H76 -> 0.035 | J76: =I76 -> 0.035 | K76: =J76 -> 0.035 | L76: =K76 -> 0.035 | ... T76: =S76 -> 0.035
B77: income return ($) | D77: =D75*D76 -> 24773 | E77: =E75*E76 -> 23552.279 | F77: =F75*F76 -> 22169.737 | G77: =G75*G76 -> 20612.537 | H77: =H75*H76 -> 18866.951 | I77: =I75*I76 -> 16918.294 | J77: =J75*J76 -> 14750.868 | K77: =K75*K76 -> 12347.89 | ... T77: =T75*T76 -> 3.9211187
B78: Tax Rate (%) | D78: =C60 -> 0.15 | E78: =D78 -> 0.15 | F78: =E78 -> 0.15 | G78: =F78 -> 0.15 | H78: =G78 -> 0.15 | I78: =H78 -> 0.15 | J78: =I78 -> 0.15 | K78: =J78 -> 0.15 | L78: =K78 -> 0.15 | ... T78: =S78 -> 0.15
B79: Tax Rate ($) | D79: =IF((D77*D78)<0,0,(D77*D78)) -> 3715.95 | E79: =IF((E77*E78)<0,0,(E77*E78)) -> 3532.8418 | F79: =IF((F77*F78)<0,0,(F77*F78)) -> 3325.4605 | G79: =IF((G77*G78)<0,0,(G77*G78)) -> 3091.8806 | H79: =IF((H77*H78)<0,0,(H77*H78)) -> 2830.0426 | I79: =IF((I77*I78)<0,0,(I77*I78)) -> 2537.7441 | J79: =IF((J77*J78)<0,0,(J77*J78)) -> 2212.6302 | K79: =IF((K77*K78)<0,0,(K77*K78)) -> 1852.1834 | ... T79: =IF((T77*T78)<0,0,(T77*T78)) -> 0.5881678 | V79: =SUM(D79:N79) -> 26097.794
B80: Income after tax | D80: =IF((D77-D79)<0,0,(D77-D79)) -> 21057.05 | E80: =IF((E77-E79)<0,0,(E77-E79)) -> 20019.437 | F80: =IF((F77-F79)<0,0,(F77-F79)) -> 18844.276 | G80: =IF((G77-G79)<0,0,(G77-G79)) -> 17520.657 | H80: =IF((H77-H79)<0,0,(H77-H79)) -> 16036.908 | I80: =IF((I77-I79)<0,0,(I77-I79)) -> 14380.55 | J80: =IF((J77-J79)<0,0,(J77-J79)) -> 12538.238 | K80: =IF((K77-K79)<0,0,(K77-K79)) -> 10495.706 | ... T80: =IF((T77-T79)<0,0,(T77-T79)) -> 3.3329509 | V80: =SUM(D80:N80) -> 147887.5
B82: Growth (%) | D82: =C67 -> 0.045 | E82: =D82 -> 0.045 | F82: =E82 -> 0.045 | G82: =F82 -> 0.045 | H82: =G82 -> 0.045 | I82: =H82 -> 0.045 | J82: =I82 -> 0.045 | K82: =J82 -> 0.045 | L82: =K82 -> 0.045 | ... T82: =S82 -> 0.045
B83: Growth ($) | D83: =IF((D82*D75)<0,0,(D82*D75)) -> 31851 | E83: =IF((E82*E75)<0,0,(E82*E75)) -> 30281.501 | F83: =IF((F82*F75)<0,0,(F82*F75)) -> 28503.947 | G83: =IF((G82*G75)<0,0,(G82*G75)) -> 26501.834 | H83: =IF((H82*H75)<0,0,(H82*H75)) -> 24257.508 | I83: =IF((I82*I75)<0,0,(I82*I75)) -> 21752.093 | J83: =IF((J82*J75)<0,0,(J82*J75)) -> 18965.402 | K83: =IF((K82*K75)<0,0,(K82*K75)) -> 15875.858 | ... T83: =IF((T82*T75)<0,0,(T82*T75)) -> 5.0414383 | V83: =SUM(D83:M83) -> 219143.92
B85: Closing Balance | D85: =D75+D80+D83 -> 760708.05 | E85: =E75+E80+E83 -> 723223.19 | F85: =F75+F80+F83 -> 680769.27 | G85: =G75+G80+G83 -> 632952.13 | H85: =H75+H80+H83 -> 579350.16 | I85: =I75+I80+I83 -> 519512.48 | J85: =J75+J80+J83 -> 452957.02 | K85: =K75+K80+K83 -> 379168.41 | ... T85: =T75+T80+T83 -> 120.40635
B87: income needed ex fees | D87: 80000 | E87: =D87*(1+D88) -> 82400 | F87: =E87*(1+E88) -> 84872 | G87: =F87*(1+F88) -> 87418.16 | H87: =G87*(1+G88) -> 90040.705 | I87: =H87*(1+H88) -> 92741.926 | J87: =I87*(1+I88) -> 95524.184 | K87: =J87*(1+J88) -> 98389.909 | L87: =K87*(1+K88) -> 101341.61 | ... T87: =S87*(1+S88) -> 128376.52
B88: Inflation assumed | D88: =C62 -> 0.03 | E88: =D88 -> 0.03 | F88: =E88 -> 0.03 | G88: =F88 -> 0.03 | H88: =G88 -> 0.03 | I88: =H88 -> 0.03 | J88: =I88 -> 0.03 | K88: =J88 -> 0.03 | L88: =K88 -> 0.03 | ... T88: =S88 -> 0.03
B90: Fees (%) | D90: =C61 -> 0.011 | E90: =D90 -> 0.011 | F90: =E90 -> 0.011 | G90: =F90 -> 0.011 | H90: =G90 -> 0.011 | I90: =H90 -> 0.011 | J90: =I90 -> 0.011 | K90: =J90 -> 0.011 | L90: =K90 -> 0.011 | ... T90: =S90 -> 0.011
B91: Fees ($) | D91: =IF((D90*D75)<0,0,(D90*D75)) -> 7785.8 | E91: =IF((E90*E75)<0,0,(E90*E75)) -> 7402.1447 | F91: =IF((F90*F75)<0,0,(F90*F75)) -> 6967.6315 | G91: =IF((G90*G75)<0,0,(G90*G75)) -> 6478.226 | H91: =IF((H90*H75)<0,0,(H90*H75)) -> 5929.6131 | I91: =IF((I90*I75)<0,0,(I90*I75)) -> 5317.1782 | J91: =IF((J90*J75)<0,0,(J90*J75)) -> 4635.9871 | K91: =IF((K90*K75)<0,0,(K90*K75)) -> 3880.7653 | ... T91: =IF((T90*T75)<0,0,(T90*T75)) -> 1.2323516 | V91: =SUM(D91:N91) -> 54681.092 | W91: =V91/V93 -> 0.050663255
B93: income needed inclusive of fees | D93: =IF(D69<=$C$51,(D87+D91),0) -> 87785.8 | E93: =IF(E69<=$C$51,(E87+E91),0) -> 89802.145 | F93: =IF(F69<=$C$51,(F87+F91),0) -> 91839.631 | G93: =IF(G69<=$C$51,(G87+G91),0) -> 93896.386 | H93: =IF(H69<=$C$51,(H87+H91),0) -> 95970.318 | I93: =IF(I69<=$C$51,(I87+I91),0) -> 98059.104 | J93: =IF(J69<=$C$51,(J87+J91),0) -> 100160.17 | K93: =IF(K69<=$C$51,(K87+K91),0) -> 102270.67 | ... T93: =IF(T69<=$C$51,(T87+T91),0) -> 0 | V93: =SUM(D93:N93) -> 1079304.7
B95: Finial Closing balance | D95: =D85-D87 -> 680708.05 | E95: =E85-E87 -> 640823.19 | F95: =F85-F87 -> 595897.27 | G95: =G85-G87 -> 545533.97 | H95: =H85-H87 -> 489309.45 | I95: =I85-I87 -> 426770.55 | J95: =J85-J87 -> 357432.83 | K95: =K85-K87 -> 280778.5 | ... T95: =T85-T87 -> -128256.11
B97: if by | D97: =D69 -> 2032
B98: I need | D98: =D75 -> 707800 | E98: in capital
B99: Assuming
B100: Portfolio | D100: Balanced | E100: "- this is a pull down menue that automatically fills in the Income % and Growth %"
B101: Portfolio Attributes
B102: income return (%) | D102: 0.035
B103: Growth (%) | D103: 0.045
B105: Stage 2 Funding at beging of Stage 1
B106: Calander Year at Stage | C106: 2026
B107: Start year | C107: 1
B108: Stage length | C108: 5
B109: Finish Year | C109: =C106+C108 -> 2031
B110: Partner 1 age | C110: 65
B111: Partner 2 age | C111: 62
B112: Tax Rate (%) | C112: 0
B113: Fees % | C113: 0.011
B114: Inflation | C114: 0.03
B116: Portfolio | C116: =C64 -> Balanced | D116: "- this is a pull down menue that automatically fills in the Income % and Growth %"
B117: Portfolio Attributes
B118: income return (%) | C118: =C66 -> 0.035
B119: Growth (%) | C119: =C67 -> 0.045
B121: Calander Year | D121: =C106 -> 2026 | E121: =D121+1 -> 2027 | F121: =E121+1 -> 2028 | G121: =F121+1 -> 2029 | H121: =G121+1 -> 2030 | I121: =H121+1 -> 2031 | J121: =I121+1 -> 2032 | K121: =J121+1 -> 2033 | L121: =K121+1 -> 2034 | M121: =L121+1 -> 2035
B122: Year | D122: 0 | E122: =D122+1 -> 1 | F122: =E122+1 -> 2 | G122: =F122+1 -> 3 | H122: =G122+1 -> 4 | I122: =H122+1 -> 5 | J122: =I122+1 -> 6 | K122: =J122+1 -> 7 | L122: =K122+1 -> 8 | M122: =L122+1 -> 9
B123: Partner 1 age | D123: =C110 -> 65 | E123: =D123+1 -> 66 | F123: =E123+1 -> 67 | G123: =F123+1 -> 68 | H123: =G123+1 -> 69 | I123: =H123+1 -> 70 | J123: =I123+1 -> 71 | K123: =J123+1 -> 72 | L123: =K123+1 -> 73 | M123: =L123+1 -> 74
B124: Partner 2 age | D124: =C111 -> 62 | E124: =D124+1 -> 63 | F124: =E124+1 -> 64 | G124: =F124+1 -> 65 | H124: =G124+1 -> 66 | I124: =H124+1 -> 67 | J124: =I124+1 -> 68 | K124: =J124+1 -> 69 | L124: =K124+1 -> 70 | M124: =L124+1 -> 71
B127: open balance | D127: 475000 | E127: =D137-D145 -> 507775 | F127: =E137-E145 -> 542811.47 | G127: =F137-F145 -> 580265.47 | H127: =G137-G145 -> 620303.78 | I127: =H137-H145 -> 663104.75 | J127: =I137-I145 -> 708858.97 | K127: =J137-J145 -> 765567.69 | L127: =K137-K145 -> 826813.11 | M127: =L137-L145 -> 892958.15
B128: income return (%) | D128: =C118 -> 0.035 | E128: =D128 -> 0.035 | F128: =E128 -> 0.035 | G128: =F128 -> 0.035 | H128: =G128 -> 0.035 | I128: =H128 -> 0.035 | J128: =I128 -> 0.035 | K128: =J128 -> 0.035 | L128: =K128 -> 0.035 | M128: =L128 -> 0.035
B129: income return ($) | D129: =D127*D128 -> 16625 | E129: =E127*E128 -> 17772.125 | F129: =F127*F128 -> 18998.402 | G129: =G127*G128 -> 20309.291 | H129: =H127*H128 -> 21710.632 | I129: =I127*I128 -> 23208.666 | J129: =J127*J128 -> 24810.064 | K129: =K127*K128 -> 26794.869 | ... M129: =M127*M128 -> 31253.535
B130: Tax Rate (%) | D130: =C112 -> 0 | E130: =D130 -> 0 | F130: =E130 -> 0 | G130: =F130 -> 0 | H130: =G130 -> 0 | I130: =H130 -> 0 | J130: =I130 -> 0 | K130: =J130 -> 0 | L130: =K130 -> 0 | M130: =L130 -> 0
B131: Tax Rate ($) | D131: =IF((D129*D130)<0,0,(D129*D130)) -> 0 | E131: =IF((E129*E130)<0,0,(E129*E130)) -> 0 | F131: =IF((F129*F130)<0,0,(F129*F130)) -> 0 | G131: =IF((G129*G130)<0,0,(G129*G130)) -> 0 | H131: =IF((H129*H130)<0,0,(H129*H130)) -> 0 | I131: =IF((I129*I130)<0,0,(I129*I130)) -> 0 | J131: =IF((J129*J130)<0,0,(J129*J130)) -> 0 | K131: =IF((K129*K130)<0,0,(K129*K130)) -> 0 | ... M131: =IF((M129*M130)<0,0,(M129*M130)) -> 0 | V131: =SUM(D131:N131) -> 0
B132: Income after tax | D132: =IF((D129-D131)<0,0,(D129-D131)) -> 16625 | E132: =IF((E129-E131)<0,0,(E129-E131)) -> 17772.125 | F132: =IF((F129-F131)<0,0,(F129-F131)) -> 18998.402 | G132: =IF((G129-G131)<0,0,(G129-G131)) -> 20309.291 | H132: =IF((H129-H131)<0,0,(H129-H131)) -> 21710.632 | I132: =IF((I129-I131)<0,0,(I129-I131)) -> 23208.666 | J132: =IF((J129-J131)<0,0,(J129-J131)) -> 24810.064 | K132: =IF((K129-K131)<0,0,(K129-K131)) -> 26794.869 | ... M132: =IF((M129-M131)<0,0,(M129-M131)) -> 31253.535 | V132: =SUM(D132:N132) -> 230421.04
...

Sheet Income - Stage 2

Sheet Income - Stage 3

Sheet Car - P1
B1: Car for Partner 1
B2: Calander Year at Stage | C2: ='Income - Stage 1'!C3 -> 2026
B3: Start year | C3: ='Income - Stage 1'!C4 -> 1
B4: Stage length | C4: 26
B5: Finish Year | C5: =C2+C4 -> 2052
B6: The year that needs to be iqual to $0 is | C6: =C5+1 -> 2053
B8: Partner 1 age at start of Stage | C8: ='Income - Stage 1'!C7 -> 65
B9: Partner 1 age at END of Stage | C9: =C8+C4 -> 91
B11: Partner 2 age at stage of stage | C11: ='Income - Stage 1'!C8 -> 62
B12: Partner 2 age at END of Stage | C12: =C11+C4 -> 88
B14: Tax Rate (%) | C14: 0.15
B15: Fees % | C15: 0.011
B16: Inflation | C16: 0.03
B18: Portfolio | C18: Balanced | D18: "- this is a pull down menue that automatically fills in the Income % and Growth %"
B19: Portfolio Attributes
B20: income return (%) | C20: 0.035
B21: Growth (%) | C21: 0.045
B23: Calander Year | D23: =C2 -> 2026 | E23: =D23+1 -> 2027 | F23: =E23+1 -> 2028 | G23: =F23+1 -> 2029 | H23: =G23+1 -> 2030 | I23: =H23+1 -> 2031 | J23: =I23+1 -> 2032 | K23: =J23+1 -> 2033 | L23: =K23+1 -> 2034 | ... AI23: =AH23+1 -> 2057
B24: Year | D24: =C3 -> 1 | E24: =D24+1 -> 2 | F24: =E24+1 -> 3 | G24: =F24+1 -> 4 | H24: =G24+1 -> 5 | I24: =H24+1 -> 6 | J24: =I24+1 -> 7 | K24: =J24+1 -> 8 | L24: =K24+1 -> 9 | ... AI24: =AH24+1 -> 32
B25: Partner 1 age | D25: =C8 -> 65 | E25: =D25+1 -> 66 | F25: =E25+1 -> 67 | G25: =F25+1 -> 68 | H25: =G25+1 -> 69 | I25: =H25+1 -> 70 | J25: =I25+1 -> 71 | K25: =J25+1 -> 72 | L25: =K25+1 -> 73 | ... AI25: =AH25+1 -> 96
B26: Partner 2 age | D26: =C11 -> 62 | E26: =D26+1 -> 63 | F26: =E26+1 -> 64 | G26: =F26+1 -> 65 | H26: =G26+1 -> 66 | I26: =H26+1 -> 67 | J26: =I26+1 -> 68 | K26: =J26+1 -> 69 | L26: =K26+1 -> 70 | ... AI26: =AH26+1 -> 93
B29: open balance | D29: 112500 | E29: =D58 -> 67609.375 | F29: =E58 -> 69363.176 | G29: =F58 -> 71248.073 | H29: =G58 -> 73273.867 | I29: =H58 -> 75451.088 | J29: =I58 -> 77791.057 | K29: =J58 -> 80305.939 | L29: =K58 -> 83008.807 | ... AI29: =AH58 -> 421.08392
B30: income return (%) | D30: =C20 -> 0.035 | E30: =D30 -> 0.035 | F30: =E30 -> 0.035 | G30: =F30 -> 0.035 | H30: =G30 -> 0.035 | I30: =H30 -> 0.035 | J30: =I30 -> 0.035 | K30: =J30 -> 0.035 | L30: =K30 -> 0.035 | ... AI30: =AH30 -> 0.035
B31: income return ($) | D31: =D29*D30 -> 3937.5 | E31: =E29*E30 -> 2366.3281 | F31: =F29*F30 -> 2427.7112 | G31: =G29*G30 -> 2493.6826 | H31: =H29*H30 -> 2564.5853 | I31: =I29*I30 -> 2640.7881 | J31: =J29*J30 -> 2722.687 | K31: =K29*K30 -> 2810.7078 | ... AI31: =AI29*AI30 -> 14.737937
B32: Tax Rate (%) | D32: =C14 -> 0.15 | E32: =D32 -> 0.15 | F32: =E32 -> 0.15 | G32: =F32 -> 0.15 | H32: =G32 -> 0.15 | I32: =H32 -> 0.15 | J32: =I32 -> 0.15 | K32: =J32 -> 0.15 | L32: =K32 -> 0.15 | ... AI32: =AH32 -> 0.15
B33: Tax Rate ($) | D33: =IF((D31*D32)<0,0,(D31*D32)) -> 590.625 | E33: =IF((E31*E32)<0,0,(E31*E32)) -> 354.94922 | F33: =IF((F31*F32)<0,0,(F31*F32)) -> 364.15667 | G33: =IF((G31*G32)<0,0,(G31*G32)) -> 374.05238 | H33: =IF((H31*H32)<0,0,(H31*H32)) -> 384.6878 | I33: =IF((I31*I32)<0,0,(I31*I32)) -> 396.11821 | J33: =IF((J31*J32)<0,0,(J31*J32)) -> 408.40305 | K33: =IF((K31*K32)<0,0,(K31*K32)) -> 421.60618 | ... AI33: =IF((AI31*AI32)<0,0,(AI31*AI32)) -> 2.2106906
B34: Income after tax | D34: =IF((D31-D33)<0,0,(D31-D33)) -> 3346.875 | E34: =IF((E31-E33)<0,0,(E31-E33)) -> 2011.3789 | F34: =IF((F31-F33)<0,0,(F31-F33)) -> 2063.5545 | G34: =IF((G31-G33)<0,0,(G31-G33)) -> 2119.6302 | H34: =IF((H31-H33)<0,0,(H31-H33)) -> 2179.8975 | I34: =IF((I31-I33)<0,0,(I31-I33)) -> 2244.6699 | J34: =IF((J31-J33)<0,0,(J31-J33)) -> 2314.2839 | K34: =IF((K31-K33)<0,0,(K31-K33)) -> 2389.1017 | ... AI34: =IF((AI31-AI33)<0,0,(AI31-AI33)) -> 12.527247
B36: Growth (%) | D36: =C21 -> 0.045 | E36: =D36 -> 0.045 | F36: =E36 -> 0.045 | G36: =F36 -> 0.045 | H36: =G36 -> 0.045 | I36: =H36 -> 0.045 | J36: =I36 -> 0.045 | K36: =J36 -> 0.045 | L36: =K36 -> 0.045 | ... AI36: =AH36 -> 0.045
B37: Growth ($) | D37: =IF((D36*D29)<0,0,(D36*D29)) -> 5062.5 | E37: =IF((E36*E29)<0,0,(E36*E29)) -> 3042.4219 | F37: =IF((F36*F29)<0,0,(F36*F29)) -> 3121.3429 | G37: =IF((G36*G29)<0,0,(G36*G29)) -> 3206.1633 | H37: =IF((H36*H29)<0,0,(H36*H29)) -> 3297.324 | I37: =IF((I36*I29)<0,0,(I36*I29)) -> 3395.299 | J37: =IF((J36*J29)<0,0,(J36*J29)) -> 3500.5976 | K37: =IF((K36*K29)<0,0,(K36*K29)) -> 3613.7672 | ... AI37: =IF((AI36*AI29)<0,0,(AI36*AI29)) -> 18.948777
B39: Closing Balance | D39: =D29+D34+D37 -> 120909.38 | E39: =E29+E34+E37 -> 72663.176 | F39: =F29+F34+F37 -> 74548.073 | G39: =G29+G34+G37 -> 76573.867 | H39: =H29+H34+H37 -> 78751.088 | I39: =I29+I34+I37 -> 81091.057 | J39: =J29+J34+J37 -> 83605.939 | K39: =K29+K34+K37 -> 86308.807 | ... AI39: =AI29+AI34+AI37 -> 452.55995
B41: Capital Needed - Purchase Price | D41: 50000 | E41: 0 | F41: 0 | G41: 0 | H41: 0 | I41: 0 | J41: 0 | K41: 0 | L41: 0 | M41: 50000 | N41: 0 | O41: 0 | P41: 0 | Q41: 0 | R41: 0 | S41: 0 | T41: 0 | U41: 0 | V41: 50000 | W41: 0 | X41: 0 | Y41: 0 | Z41: 0 | AA41: 0 | AB41: 0 | AC41: 0 | AD41: 0 | AE41: 0 | AF41: 0 | AG41: 0 | AH41: 0 | AI41: 0
B42: Trade in Value | D42: 0 | M42: 10000 | V42: 10000 | AC42: 0 | AD42: 10000
B43: Holding Cost
B44: Rego | C44: 500
B45: Insurance | C45: 1200
B46: Maintenance | C46: 1000
B47: Services | C47: 600
B48: Hollding Costs - Total | C48: =SUM(C44:C47) -> 3300 | D48: =IF(D23<$C$6,C48,0) -> 3300 | E48: =IF(E23<$C$6,D48,0) -> 3300 | F48: =IF(F23<$C$6,E48,0) -> 3300 | G48: =IF(G23<$C$6,F48,0) -> 3300 | H48: =IF(H23<$C$6,G48,0) -> 3300 | I48: =IF(I23<$C$6,H48,0) -> 3300 | J48: =IF(J23<$C$6,I48,0) -> 3300 | K48: =IF(K23<$C$6,J48,0) -> 3300 | ... AI48: =IF(AI23<$C$6,AH48,0) -> 0
B50: income needed ex fees | D50: =D41-D42+D48 -> 53300 | E50: =E41-E42+E48 -> 3300 | F50: =F41-F42+F48 -> 3300 | G50: =G41-G42+G48 -> 3300 | H50: =H41-H42+H48 -> 3300 | I50: =I41-I42+I48 -> 3300 | J50: =J41-J42+J48 -> 3300 | K50: =K41-K42+K48 -> 3300 | ... AI50: =AI41-AI42+AI48 -> 0
B51: Inflation assumed | D51: =C16 -> 0.03 | E51: =D51 -> 0.03 | F51: =E51 -> 0.03 | G51: =F51 -> 0.03 | H51: =G51 -> 0.03 | I51: =H51 -> 0.03 | J51: =I51 -> 0.03 | K51: =J51 -> 0.03 | L51: =K51 -> 0.03 | ... AI51: =AH51 -> 0.03
B53: Fees (%) | D53: =C15 -> 0.011 | E53: =D53 -> 0.011 | F53: =E53 -> 0.011 | G53: =F53 -> 0.011 | H53: =G53 -> 0.011 | I53: =H53 -> 0.011 | J53: =I53 -> 0.011 | K53: =J53 -> 0.011 | L53: =K53 -> 0.011 | ... AI53: =AH53 -> 0.011
B54: Fees ($) | D54: =IF((D53*D29)<0,0,(D53*D29)) -> 1237.5 | E54: =IF((E53*E29)<0,0,(E53*E29)) -> 743.70312 | F54: =IF((F53*F29)<0,0,(F53*F29)) -> 762.99493 | G54: =IF((G53*G29)<0,0,(G53*G29)) -> 783.7288 | H54: =IF((H53*H29)<0,0,(H53*H29)) -> 806.01253 | I54: =IF((I53*I29)<0,0,(I53*I29)) -> 829.96197 | J54: =IF((J53*J29)<0,0,(J53*J29)) -> 855.70163 | K54: =IF((K53*K29)<0,0,(K53*K29)) -> 883.36532 | ... AI54: =IF((AI53*AI29)<0,0,(AI53*AI29)) -> 4.6319231 | AJ54: =AI54/AI56 -> #DIV/0!
B56: income needed inclusive of fees | D56: =IF(D23<=$C$60,(D50+D54),0) -> 0 | E56: =IF(E23<=$C$60,(E50+E54),0) -> 0 | F56: =IF(F23<=$C$60,(F50+F54),0) -> 0 | G56: =IF(G23<=$C$60,(G50+G54),0) -> 0 | H56: =IF(H23<=$C$60,(H50+H54),0) -> 0 | I56: =IF(I23<=$C$60,(I50+I54),0) -> 0 | J56: =IF(J23<=$C$60,(J50+J54),0) -> 0 | K56: =IF(K23<=$C$60,(K50+K54),0) -> 0 | ... AI56: =IF(AI23<=$C$60,(AI50+AI54),0) -> 0
B58: Finial Closing balance | D58: =D39-D50 -> 67609.375 | E58: =E39-E50 -> 69363.176 | F58: =F39-F50 -> 71248.073 | G58: =G39-G50 -> 73273.867 | H58: =H39-H50 -> 75451.088 | I58: =I39-I50 -> 77791.057 | J58: =J39-J50 -> 80305.939 | K58: =K39-K50 -> 83008.807 | ... AI58: =AI39-AI50 -> 452.55995
B60: if by | D60: =D23 -> 2026
B61: I need | D61: =D29 -> 112500 | E61: in capital
B62: Assuming
B63: Portfolio | D63: Balanced | E63: "- this is a pull down menue that automatically fills in the Income % and Growth %"
B64: Portfolio Attributes
B65: income return (%) | D65: 0.035
B66: Growth (%) | D66: 0.045
B68: Stage 2 Funding at beging of Stage 1
B69: Calander Year at Stage | C69: 2026
B70: Start year | C70: 1
B71: Stage length | C71: 5
B72: Finish Year | C72: =C69+C71 -> 2031
B73: Partner 1 age | C73: 65
B74: Partner 2 age | C74: 62
B75: Tax Rate (%) | C75: 0
B76: Fees % | C76: 0.011
B77: Inflation | C77: 0.03
B79: Portfolio | C79: =C18 -> Balanced | D79: "- this is a pull down menue that automatically fills in the Income % and Growth %"
B80: Portfolio Attributes
B81: income return (%) | C81: =C20 -> 0.035
B82: Growth (%) | C82: =C21 -> 0.045
B84: Calander Year | D84: =C69 -> 2026 | E84: =D84+1 -> 2027 | F84: =E84+1 -> 2028 | G84: =F84+1 -> 2029 | H84: =G84+1 -> 2030 | I84: =H84+1 -> 2031 | J84: =I84+1 -> 2032 | K84: =J84+1 -> 2033 | L84: =K84+1 -> 2034 | M84: =L84+1 -> 2035
B85: Year | D85: 0 | E85: =D85+1 -> 1 | F85: =E85+1 -> 2 | G85: =F85+1 -> 3 | H85: =G85+1 -> 4 | I85: =H85+1 -> 5 | J85: =I85+1 -> 6 | K85: =J85+1 -> 7 | L85: =K85+1 -> 8 | M85: =L85+1 -> 9
B86: Partner 1 age | D86: =C73 -> 65 | E86: =D86+1 -> 66 | F86: =E86+1 -> 67 | G86: =F86+1 -> 68 | H86: =G86+1 -> 69 | I86: =H86+1 -> 70 | J86: =I86+1 -> 71 | K86: =J86+1 -> 72 | L86: =K86+1 -> 73 | M86: =L86+1 -> 74
B87: Partner 2 age | D87: =C74 -> 62 | E87: =D87+1 -> 63 | F87: =E87+1 -> 64 | G87: =F87+1 -> 65 | H87: =G87+1 -> 66 | I87: =H87+1 -> 67 | J87: =I87+1 -> 68 | K87: =J87+1 -> 69 | L87: =K87+1 -> 70 | M87: =L87+1 -> 71
B90: open balance | D90: 475000 | E90: =D100-D108 -> 507775 | F90: =E100-E108 -> 542811.47 | G90: =F100-F108 -> 580265.47 | H90: =G100-G108 -> 620303.78 | I90: =H100-H108 -> 663104.75 | J90: =I100-I108 -> 708858.97 | K90: =J100-J108 -> 757770.24 | L90: =K100-K108 -> 810056.39 | M90: =L100-L108 -> 865950.28
B91: income return (%) | D91: =C81 -> 0.035 | E91: =D91 -> 0.035 | F91: =E91 -> 0.035 | G91: =F91 -> 0.035 | H91: =G91 -> 0.035 | I91: =H91 -> 0.035 | J91: =I91 -> 0.035 | K91: =J91 -> 0.035 | L91: =K91 -> 0.035 | M91: =L91 -> 0.035
B92: income return ($) | D92: =D90*D91 -> 16625 | E92: =E90*E91 -> 17772.125 | F92: =F90*F91 -> 18998.402 | G92: =G90*G91 -> 20309.291 | H92: =H90*H91 -> 21710.632 | I92: =I90*I91 -> 23208.666 | J92: =J90*J91 -> 24810.064 | K92: =K90*K91 -> 26521.958 | ... M92: =M90*M91 -> 30308.26
B93: Tax Rate (%) | D93: =C75 -> 0 | E93: =D93 -> 0 | F93: =E93 -> 0 | G93: =F93 -> 0 | H93: =G93 -> 0 | I93: =H93 -> 0 | J93: =I93 -> 0 | K93: =J93 -> 0 | L93: =K93 -> 0 | M93: =L93 -> 0
B94: Tax Rate ($) | D94: =IF((D92*D93)<0,0,(D92*D93)) -> 0 | E94: =IF((E92*E93)<0,0,(E92*E93)) -> 0 | F94: =IF((F92*F93)<0,0,(F92*F93)) -> 0 | G94: =IF((G92*G93)<0,0,(G92*G93)) -> 0 | H94: =IF((H92*H93)<0,0,(H92*H93)) -> 0 | I94: =IF((I92*I93)<0,0,(I92*I93)) -> 0 | J94: =IF((J92*J93)<0,0,(J92*J93)) -> 0 | K94: =IF((K92*K93)<0,0,(K92*K93)) -> 0 | ... M94: =IF((M92*M93)<0,0,(M92*M93)) -> 0 | AI94: =SUM(D94:N94) -> 0
B95: Income after tax | D95: =IF((D92-D94)<0,0,(D92-D94)) -> 16625 | E95: =IF((E92-E94)<0,0,(E92-E94)) -> 17772.125 | F95: =IF((F92-F94)<0,0,(F92-F94)) -> 18998.402 | G95: =IF((G92-G94)<0,0,(G92-G94)) -> 20309.291 | H95: =IF((H92-H94)<0,0,(H92-H94)) -> 21710.632 | I95: =IF((I92-I94)<0,0,(I92-I94)) -> 23208.666 | J95: =IF((J92-J94)<0,0,(J92-J94)) -> 24810.064 | K95: =IF((K92-K94)<0,0,(K92-K94)) -> 26521.958 | ... M95: =IF((M92-M94)<0,0,(M92-M94)) -> 30308.26 | AI95: =SUM(D95:N95) -> 228616.37
B97: Growth (%) | D97: =C82 -> 0.045 | E97: =D97 -> 0.045 | F97: =E97 -> 0.045 | G97: =F97 -> 0.045 | H97: =G97 -> 0.045 | I97: =H97 -> 0.045 | J97: =I97 -> 0.045 | K97: =J97 -> 0.045 | L97: =K97 -> 0.045 | M97: =L97 -> 0.045
B98: Growth ($) | D98: =IF((D97*D90)<0,0,(D97*D90)) -> 21375 | E98: =IF((E97*E90)<0,0,(E97*E90)) -> 22849.875 | F98: =IF((F97*F90)<0,0,(F97*F90)) -> 24426.516 | G98: =IF((G97*G90)<0,0,(G97*G90)) -> 26111.946 | H98: =IF((H97*H90)<0,0,(H97*H90)) -> 27913.67 | I98: =IF((I97*I90)<0,0,(I97*I90)) -> 29839.714 | J98: =IF((J97*J90)<0,0,(J97*J90)) -> 31898.654 | K98: =IF((K97*K90)<0,0,(K97*K90)) -> 34099.661 | ... M98: =IF((M97*M90)<0,0,(M97*M90)) -> 38967.763 | AI98: =SUM(D98:M98) -> 293935.34
B100: Closing Balance | D100: =D90+D95+D98 -> 513000 | E100: =E90+E95+E98 -> 548397 | F100: =F90+F95+F98 -> 586236.39 | G100: =G90+G95+G98 -> 626686.7 | H100: =H90+H95+H98 -> 669928.09 | I100: =I90+I95+I98 -> 716153.12 | J100: =J90+J95+J98 -> 765567.69 | K100: =K90+K95+K98 -> 818391.86 | ... M100: =M90+M95+M98 -> 935226.3
B102: income needed ex fees | D102: 0 | E102: =D102*(1+D103) -> 0 | F102: =E102*(1+E103) -> 0 | G102: =F102*(1+F103) -> 0 | H102: =G102*(1+G103) -> 0 | I102: =H102*(1+H103) -> 0 | J102: =I102*(1+I103) -> 0 | K102: =J102*(1+J103) -> 0 | L102: =K102*(1+K103) -> 0 | M102: =L102*(1+L103) -> 0
B103: Inflation assumed | D103: =C77 -> 0.03 | E103: =D103 -> 0.03 | F103: =E103 -> 0.03 | G103: =F103 -> 0.03 | H103: =G103 -> 0.03 | I103: =H103 -> 0.03 | J103: =I103 -> 0.03 | K103: =J103 -> 0.03 | L103: =K103 -> 0.03 | M103: =L103 -> 0.03
B105: Fees (%) | D105: =C76 -> 0.011 | E105: =D105 -> 0.011 | F105: =E105 -> 0.011 | G105: =F105 -> 0.011 | H105: =G105 -> 0.011 | I105: =H105 -> 0.011 | J105: =I105 -> 0.011 | K105: =J105 -> 0.011 | L105: =K105 -> 0.011 | M105: =L105 -> 0.011
B106: Fees ($) | D106: =IF((D105*D90)<0,0,(D105*D90)) -> 5225 | E106: =IF((E105*E90)<0,0,(E105*E90)) -> 5585.525 | F106: =IF((F105*F90)<0,0,(F105*F90)) -> 5970.9262 | G106: =IF((G105*G90)<0,0,(G105*G90)) -> 6382.9201 | H106: =IF((H105*H90)<0,0,(H105*H90)) -> 6823.3416 | I106: =IF((I105*I90)<0,0,(I105*I90)) -> 7294.1522 | J106: =IF((J105*J90)<0,0,(J105*J90)) -> 7797.4487 | K106: =IF((K105*K90)<0,0,(K105*K90)) -> 8335.4727 | ... M106: =IF((M105*M90)<0,0,(M105*M90)) -> 9525.4531 | AI106: =SUM(D106:N106) -> 71850.86 | AJ106: =AI106/AI108 -> 1
B108: income needed inclusive of fees | D108: =IF(D85<=$C$5,(D102+D106),0) -> 5225 | E108: =IF(E85<=$C$5,(E102+E106),0) -> 5585.525 | F108: =IF(F85<=$C$5,(F102+F106),0) -> 5970.9262 | G108: =IF(G85<=$C$5,(G102+G106),0) -> 6382.9201 | H108: =IF(H85<=$C$5,(H102+H106),0) -> 6823.3416 | I108: =IF(I85<=$C$5,(I102+I106),0) -> 7294.1522 | J108: =IF(J85<=$C$5,(J102+J106),0) -> 7797.4487 | K108: =IF(K85<=$C$5,(K102+K106),0) -> 8335.4727 | ... M108: =IF(M85<=$C$5,(M102+M106),0) -> 9525.4531 | AI108: =SUM(D108:N108) -> 71850.86
B110: Finial Closing balance | D110: =D100-D102 -> 513000 | E110: =E100-E102 -> 548397 | F110: =F100-F102 -> 586236.39 | G110: =G100-G102 -> 626686.7 | H110: =H100-H102 -> 669928.09 | I110: =I100-I102 -> 716153.12 | J110: =J100-J102 -> 765567.69 | K110: =K100-K102 -> 818391.86 | ... M110: =M100-M102 -> 935226.3

Sheet Car P2
B1: Car for Partner 2
B2: Calander Year at Stage | C2: ='Income - Stage 1'!C3 -> 2026
B3: Start year | C3: ='Income - Stage 1'!C4 -> 1
B4: Stage length | C4: 19
B5: Finish Year | C5: =C2+C4 -> 2045
B6: The year that needs to be iqual to $0 is | C6: =C5+1 -> 2046
B8: Partner 1 age at start of Stage | C8: ='Income - Stage 1'!C7 -> 65
B9: Partner 1 age at END of Stage | C9: =C8+C4 -> 84
B11: Partner 2 age at stage of stage | C11: ='Income - Stage 1'!C8 -> 62
B12: Partner 2 age at END of Stage | C12: =C11+C4 -> 81
B14: Tax Rate (%) | C14: 0.15
B15: Fees % | C15: 0.011
B16: Inflation | C16: 0.03
B18: Portfolio | C18: Balanced | D18: "- this is a pull down menue that automatically fills in the Income % and Growth %"
B19: Portfolio Attributes
B20: income return (%) | C20: 0.035
B21: Growth (%) | C21: 0.045
B23: Calander Year | D23: =C2 -> 2026 | E23: =D23+1 -> 2027 | F23: =E23+1 -> 2028 | G23: =F23+1 -> 2029 | H23: =G23+1 -> 2030 | I23: =H23+1 -> 2031 | J23: =I23+1 -> 2032 | K23: =J23+1 -> 2033 | L23: =K23+1 -> 2034 | ... AI23: =AH23+1 -> 2057
B24: Year | D24: =C3 -> 1 | E24: =D24+1 -> 2 | F24: =E24+1 -> 3 | G24: =F24+1 -> 4 | H24: =G24+1 -> 5 | I24: =H24+1 -> 6 | J24: =I24+1 -> 7 | K24: =J24+1 -> 8 | L24: =K24+1 -> 9 | ... AI24: =AH24+1 -> 32
B25: Partner 1 age | D25: =C8 -> 65 | E25: =D25+1 -> 66 | F25: =E25+1 -> 67 | G25: =F25+1 -> 68 | H25: =G25+1 -> 69 | I25: =H25+1 -> 70 | J25: =I25+1 -> 71 | K25: =J25+1 -> 72 | L25: =K25+1 -> 73 | ... AI25: =AH25+1 -> 96
B26: Partner 2 age | D26: =C11 -> 62 | E26: =D26+1 -> 63 | F26: =E26+1 -> 64 | G26: =F26+1 -> 65 | H26: =G26+1 -> 66 | I26: =H26+1 -> 67 | J26: =I26+1 -> 68 | K26: =J26+1 -> 69 | L26: =K26+1 -> 70 | ... AI26: =AH26+1 -> 93
B29: open balance | D29: 96200 | E29: =D58 -> 50090.95 | F29: =E58 -> 50535.249 | G29: =F58 -> 51012.758 | H29: =G58 -> 51525.962 | I29: =H58 -> 52077.528 | J29: =I58 -> 52670.323 | K29: =J58 -> 53307.43 | L29: =K58 -> 53992.16 | ... AI29: =AH58 -> -3161.4673
B30: income return (%) | D30: =C20 -> 0.035 | E30: =D30 -> 0.035 | F30: =E30 -> 0.035 | G30: =F30 -> 0.035 | H30: =G30 -> 0.035 | I30: =H30 -> 0.035 | J30: =I30 -> 0.035 | K30: =J30 -> 0.035 | L30: =K30 -> 0.035 | ... AI30: =AH30 -> 0.035
B31: income return ($) | D31: =D29*D30 -> 3367 | E31: =E29*E30 -> 1753.1833 | F31: =F29*F30 -> 1768.7337 | G31: =G29*G30 -> 1785.4465 | H31: =H29*H30 -> 1803.4087 | I31: =I29*I30 -> 1822.7135 | J31: =J29*J30 -> 1843.4613 | K31: =K29*K30 -> 1865.76 | ... AI31: =AI29*AI30 -> -110.65136
B32: Tax Rate (%) | D32: =C14 -> 0.15 | E32: =D32 -> 0.15 | F32: =E32 -> 0.15 | G32: =F32 -> 0.15 | H32: =G32 -> 0.15 | I32: =H32 -> 0.15 | J32: =I32 -> 0.15 | K32: =J32 -> 0.15 | L32: =K32 -> 0.15 | ... AI32: =AH32 -> 0.15
B33: Tax Rate ($) | D33: =IF((D31*D32)<0,0,(D31*D32)) -> 505.05 | E33: =IF((E31*E32)<0,0,(E31*E32)) -> 262.97749 | F33: =IF((F31*F32)<0,0,(F31*F32)) -> 265.31005 | G33: =IF((G31*G32)<0,0,(G31*G32)) -> 267.81698 | H33: =IF((H31*H32)<0,0,(H31*H32)) -> 270.5113 | I33: =IF((I31*I32)<0,0,(I31*I32)) -> 273.40702 | J33: =IF((J31*J32)<0,0,(J31*J32)) -> 276.5192 | K33: =IF((K31*K32)<0,0,(K31*K32)) -> 279.864 | ... AI33: =IF((AI31*AI32)<0,0,(AI31*AI32)) -> 0
B34: Income after tax | D34: =IF((D31-D33)<0,0,(D31-D33)) -> 2861.95 | E34: =IF((E31-E33)<0,0,(E31-E33)) -> 1490.2058 | F34: =IF((F31-F33)<0,0,(F31-F33)) -> 1503.4236 | G34: =IF((G31-G33)<0,0,(G31-G33)) -> 1517.6296 | H34: =IF((H31-H33)<0,0,(H31-H33)) -> 1532.8974 | I34: =IF((I31-I33)<0,0,(I31-I33)) -> 1549.3064 | J34: =IF((J31-J33)<0,0,(J31-J33)) -> 1566.9421 | K34: =IF((K31-K33)<0,0,(K31-K33)) -> 1585.896 | ... AI34: =IF((AI31-AI33)<0,0,(AI31-AI33)) -> 0
B36: Growth (%) | D36: =C21 -> 0.045 | E36: =D36 -> 0.045 | F36: =E36 -> 0.045 | G36: =F36 -> 0.045 | H36: =G36 -> 0.045 | I36: =H36 -> 0.045 | J36: =I36 -> 0.045 | K36: =J36 -> 0.045 | L36: =K36 -> 0.045 | ... AI36: =AH36 -> 0.045
B37: Growth ($) | D37: =IF((D36*D29)<0,0,(D36*D29)) -> 4329 | E37: =IF((E36*E29)<0,0,(E36*E29)) -> 2254.0927 | F37: =IF((F36*F29)<0,0,(F36*F29)) -> 2274.0862 | G37: =IF((G36*G29)<0,0,(G36*G29)) -> 2295.5741 | H37: =IF((H36*H29)<0,0,(H36*H29)) -> 2318.6683 | I37: =IF((I36*I29)<0,0,(I36*I29)) -> 2343.4887 | J37: =IF((J36*J29)<0,0,(J36*J29)) -> 2370.1645 | K37: =IF((K36*K29)<0,0,(K36*K29)) -> 2398.8343 | ... AI37: =IF((AI36*AI29)<0,0,(AI36*AI29)) -> 0
B39: Closing Balance | D39: =D29+D34+D37 -> 103390.95 | E39: =E29+E34+E37 -> 53835.249 | F39: =F29+F34+F37 -> 54312.758 | G39: =G29+G34+G37 -> 54825.962 | H39: =H29+H34+H37 -> 55377.528 | I39: =I29+I34+I37 -> 55970.323 | J39: =J29+J34+J37 -> 56607.43 | K39: =K29+K34+K37 -> 57292.16 | ... AI39: =AI29+AI34+AI37 -> -3161.4673
B41: Capital Needed - Purchase Price | D41: 50000 | E41: 0 | F41: 0 | G41: 0 | H41: 0 | I41: 0 | J41: 0 | K41: 0 | L41: 0 | M41: 50000 | N41: 0 | O41: 0 | P41: 0 | Q41: 0 | R41: 0 | S41: 0 | T41: 0 | U41: 0 | V41: 0 | W41: 0 | X41: 0 | Y41: 0 | Z41: 0 | AA41: 0 | AB41: 0 | AC41: 0 | AD41: 0 | AE41: 0 | AF41: 0 | AG41: 0 | AH41: 0 | AI41: 0
B42: Trade in Value | D42: 0 | M42: 10000 | V42: 10000 | AC42: 0
B43: Holding Cost
B44: Rego | C44: 500
B45: Insurance | C45: 1200
B46: Maintenance | C46: 1000
B47: Services | C47: 600
B48: Hollding Costs - Total | C48: =SUM(C44:C47) -> 3300 | D48: =IF(D23<$C$6,C48,0) -> 3300 | E48: =IF(E23<$C$6,D48,0) -> 3300 | F48: =IF(F23<$C$6,E48,0) -> 3300 | G48: =IF(G23<$C$6,F48,0) -> 3300 | H48: =IF(H23<$C$6,G48,0) -> 3300 | I48: =IF(I23<$C$6,H48,0) -> 3300 | J48: =IF(J23<$C$6,I48,0) -> 3300 | K48: =IF(K23<$C$6,J48,0) -> 3300 | ... AI48: =IF(AI23<$C$6,AH48,0) -> 0
B50: income needed ex fees | D50: =D41-D42+D48 -> 53300 | E50: =E41-E42+E48 -> 3300 | F50: =F41-F42+F48 -> 3300 | G50: =G41-G42+G48 -> 3300 | H50: =H41-H42+H48 -> 3300 | I50: =I41-I42+I48 -> 3300 | J50: =J41-J42+J48 -> 3300 | K50: =K41-K42+K48 -> 3300 | ... AI50: =AI41-AI42+AI48 -> 0
B51: Inflation assumed | D51: =C16 -> 0.03 | E51: =D51 -> 0.03 | F51: =E51 -> 0.03 | G51: =F51 -> 0.03 | H51: =G51 -> 0.03 | I51: =H51 -> 0.03 | J51: =I51 -> 0.03 | K51: =J51 -> 0.03 | L51: =K51 -> 0.03 | ... AI51: =AH51 -> 0.03
B53: Fees (%) | D53: =C15 -> 0.011 | E53: =D53 -> 0.011 | F53: =E53 -> 0.011 | G53: =F53 -> 0.011 | H53: =G53 -> 0.011 | I53: =H53 -> 0.011 | J53: =I53 -> 0.011 | K53: =J53 -> 0.011 | L53: =K53 -> 0.011 | ... AI53: =AH53 -> 0.011
B54: Fees ($) | D54: =IF((D53*D29)<0,0,(D53*D29)) -> 1058.2 | E54: =IF((E53*E29)<0,0,(E53*E29)) -> 551.00045 | F54: =IF((F53*F29)<0,0,(F53*F29)) -> 555.88773 | G54: =IF((G53*G29)<0,0,(G53*G29)) -> 561.14034 | H54: =IF((H53*H29)<0,0,(H53*H29)) -> 566.78558 | I54: =IF((I53*I29)<0,0,(I53*I29)) -> 572.8528 | J54: =IF((J53*J29)<0,0,(J53*J29)) -> 579.37355 | K54: =IF((K53*K29)<0,0,(K53*K29)) -> 586.38172 | ... AI54: =IF((AI53*AI29)<0,0,(AI53*AI29)) -> 0 | AJ54: =AI54/AI56 -> #DIV/0!
B56: income needed inclusive of fees | D56: =IF(D23<=$C$60,(D50+D54),0) -> 0 | E56: =IF(E23<=$C$60,(E50+E54),0) -> 0 | F56: =IF(F23<=$C$60,(F50+F54),0) -> 0 | G56: =IF(G23<=$C$60,(G50+G54),0) -> 0 | H56: =IF(H23<=$C$60,(H50+H54),0) -> 0 | I56: =IF(I23<=$C$60,(I50+I54),0) -> 0 | J56: =IF(J23<=$C$60,(J50+J54),0) -> 0 | K56: =IF(K23<=$C$60,(K50+K54),0) -> 0 | ... AI56: =IF(AI23<=$C$60,(AI50+AI54),0) -> 0
B58: Finial Closing balance | D58: =D39-D50 -> 50090.95 | E58: =E39-E50 -> 50535.249 | F58: =F39-F50 -> 51012.758 | G58: =G39-G50 -> 51525.962 | H58: =H39-H50 -> 52077.528 | I58: =I39-I50 -> 52670.323 | J58: =J39-J50 -> 53307.43 | K58: =K39-K50 -> 53992.16 | ... AI58: =AI39-AI50 -> -3161.4673
B60: if by | D60: =D23 -> 2026
B61: I need | D61: =D29 -> 96200 | E61: in capital
B62: Assuming
B63: Portfolio | D63: Balanced | E63: "- this is a pull down menue that automatically fills in the Income % and Growth %"
B64: Portfolio Attributes
B65: income return (%) | D65: 0.035
B66: Growth (%) | D66: 0.045
B68: Stage 2 Funding at beging of Stage 1
B69: Calander Year at Stage | C69: 2026
B70: Start year | C70: 1
B71: Stage length | C71: 5
B72: Finish Year | C72: =C69+C71 -> 2031
B73: Partner 1 age | C73: 65
B74: Partner 2 age | C74: 62
B75: Tax Rate (%) | C75: 0
B76: Fees % | C76: 0.011
B77: Inflation | C77: 0.03
B79: Portfolio | C79: =C18 -> Balanced | D79: "- this is a pull down menue that automatically fills in the Income % and Growth %"
B80: Portfolio Attributes
B81: income return (%) | C81: =C20 -> 0.035
B82: Growth (%) | C82: =C21 -> 0.045
B84: Calander Year | D84: =C69 -> 2026 | E84: =D84+1 -> 2027 | F84: =E84+1 -> 2028 | G84: =F84+1 -> 2029 | H84: =G84+1 -> 2030 | I84: =H84+1 -> 2031 | J84: =I84+1 -> 2032 | K84: =J84+1 -> 2033 | L84: =K84+1 -> 2034 | M84: =L84+1 -> 2035
B85: Year | D85: 0 | E85: =D85+1 -> 1 | F85: =E85+1 -> 2 | G85: =F85+1 -> 3 | H85: =G85+1 -> 4 | I85: =H85+1 -> 5 | J85: =I85+1 -> 6 | K85: =J85+1 -> 7 | L85: =K85+1 -> 8 | M85: =L85+1 -> 9
B86: Partner 1 age | D86: =C73 -> 65 | E86: =D86+1 -> 66 | F86: =E86+1 -> 67 | G86: =F86+1 -> 68 | H86: =G86+1 -> 69 | I86: =H86+1 -> 70 | J86: =I86+1 -> 71 | K86: =J86+1 -> 72 | L86: =K86+1 -> 73 | M86: =L86+1 -> 74
B87: Partner 2 age | D87: =C74 -> 62 | E87: =D87+1 -> 63 | F87: =E87+1 -> 64 | G87: =F87+1 -> 65 | H87: =G87+1 -> 66 | I87: =H87+1 -> 67 | J87: =I87+1 -> 68 | K87: =J87+1 -> 69 | L87: =K87+1 -> 70 | M87: =L87+1 -> 71
B90: open balance | D90: 475000 | E90: =D100-D108 -> 507775 | F90: =E100-E108 -> 542811.47 | G90: =F100-F108 -> 580265.47 | H90: =G100-G108 -> 620303.78 | I90: =H100-H108 -> 663104.75 | J90: =I100-I108 -> 708858.97 | K90: =J100-J108 -> 757770.24 | L90: =K100-K108 -> 810056.39 | M90: =L100-L108 -> 865950.28
B91: income return (%) | D91: =C81 -> 0.035 | E91: =D91 -> 0.035 | F91: =E91 -> 0.035 | G91: =F91 -> 0.035 | H91: =G91 -> 0.035 | I91: =H91 -> 0.035 | J91: =I91 -> 0.035 | K91: =J91 -> 0.035 | L91: =K91 -> 0.035 | M91: =L91 -> 0.035
B92: income return ($) | D92: =D90*D91 -> 16625 | E92: =E90*E91 -> 17772.125 | F92: =F90*F91 -> 18998.402 | G92: =G90*G91 -> 20309.291 | H92: =H90*H91 -> 21710.632 | I92: =I90*I91 -> 23208.666 | J92: =J90*J91 -> 24810.064 | K92: =K90*K91 -> 26521.958 | ... M92: =M90*M91 -> 30308.26
B93: Tax Rate (%) | D93: =C75 -> 0 | E93: =D93 -> 0 | F93: =E93 -> 0 | G93: =F93 -> 0 | H93: =G93 -> 0 | I93: =H93 -> 0 | J93: =I93 -> 0 | K93: =J93 -> 0 | L93: =K93 -> 0 | M93: =L93 -> 0
B94: Tax Rate ($) | D94: =IF((D92*D93)<0,0,(D92*D93)) -> 0 | E94: =IF((E92*E93)<0,0,(E92*E93)) -> 0 | F94: =IF((F92*F93)<0,0,(F92*F93)) -> 0 | G94: =IF((G92*G93)<0,0,(G92*G93)) -> 0 | H94: =IF((H92*H93)<0,0,(H92*H93)) -> 0 | I94: =IF((I92*I93)<0,0,(I92*I93)) -> 0 | J94: =IF((J92*J93)<0,0,(J92*J93)) -> 0 | K94: =IF((K92*K93)<0,0,(K92*K93)) -> 0 | ... M94: =IF((M92*M93)<0,0,(M92*M93)) -> 0 | AI94: =SUM(D94:N94) -> 0
B95: Income after tax | D95: =IF((D92-D94)<0,0,(D92-D94)) -> 16625 | E95: =IF((E92-E94)<0,0,(E92-E94)) -> 17772.125 | F95: =IF((F92-F94)<0,0,(F92-F94)) -> 18998.402 | G95: =IF((G92-G94)<0,0,(G92-G94)) -> 20309.291 | H95: =IF((H92-H94)<0,0,(H92-H94)) -> 21710.632 | I95: =IF((I92-I94)<0,0,(I92-I94)) -> 23208.666 | J95: =IF((J92-J94)<0,0,(J92-J94)) -> 24810.064 | K95: =IF((K92-K94)<0,0,(K92-K94)) -> 26521.958 | ... M95: =IF((M92-M94)<0,0,(M92-M94)) -> 30308.26 | AI95: =SUM(D95:N95) -> 228616.37
B97: Growth (%) | D97: =C82 -> 0.045 | E97: =D97 -> 0.045 | F97: =E97 -> 0.045 | G97: =F97 -> 0.045 | H97: =G97 -> 0.045 | I97: =H97 -> 0.045 | J97: =I97 -> 0.045 | K97: =J97 -> 0.045 | L97: =K97 -> 0.045 | M97: =L97 -> 0.045
B98: Growth ($) | D98: =IF((D97*D90)<0,0,(D97*D90)) -> 21375 | E98: =IF((E97*E90)<0,0,(E97*E90)) -> 22849.875 | F98: =IF((F97*F90)<0,0,(F97*F90)) -> 24426.516 | G98: =IF((G97*G90)<0,0,(G97*G90)) -> 26111.946 | H98: =IF((H97*H90)<0,0,(H97*H90)) -> 27913.67 | I98: =IF((I97*I90)<0,0,(I97*I90)) -> 29839.714 | J98: =IF((J97*J90)<0,0,(J97*J90)) -> 31898.654 | K98: =IF((K97*K90)<0,0,(K97*K90)) -> 34099.661 | ... M98: =IF((M97*M90)<0,0,(M97*M90)) -> 38967.763 | AI98: =SUM(D98:M98) -> 293935.34
B100: Closing Balance | D100: =D90+D95+D98 -> 513000 | E100: =E90+E95+E98 -> 548397 | F100: =F90+F95+F98 -> 586236.39 | G100: =G90+G95+G98 -> 626686.7 | H100: =H90+H95+H98 -> 669928.09 | I100: =I90+I95+I98 -> 716153.12 | J100: =J90+J95+J98 -> 765567.69 | K100: =K90+K95+K98 -> 818391.86 | ... M100: =M90+M95+M98 -> 935226.3
B102: income needed ex fees | D102: 0 | E102: =D102*(1+D103) -> 0 | F102: =E102*(1+E103) -> 0 | G102: =F102*(1+F103) -> 0 | H102: =G102*(1+G103) -> 0 | I102: =H102*(1+H103) -> 0 | J102: =I102*(1+I103) -> 0 | K102: =J102*(1+J103) -> 0 | L102: =K102*(1+K103) -> 0 | M102: =L102*(1+L103) -> 0
B103: Inflation assumed | D103: =C77 -> 0.03 | E103: =D103 -> 0.03 | F103: =E103 -> 0.03 | G103: =F103 -> 0.03 | H103: =G103 -> 0.03 | I103: =H103 -> 0.03 | J103: =I103 -> 0.03 | K103: =J103 -> 0.03 | L103: =K103 -> 0.03 | M103: =L103 -> 0.03
B105: Fees (%) | D105: =C76 -> 0.011 | E105: =D105 -> 0.011 | F105: =E105 -> 0.011 | G105: =F105 -> 0.011 | H105: =G105 -> 0.011 | I105: =H105 -> 0.011 | J105: =I105 -> 0.011 | K105: =J105 -> 0.011 | L105: =K105 -> 0.011 | M105: =L105 -> 0.011
B106: Fees ($) | D106: =IF((D105*D90)<0,0,(D105*D90)) -> 5225 | E106: =IF((E105*E90)<0,0,(E105*E90)) -> 5585.525 | F106: =IF((F105*F90)<0,0,(F105*F90)) -> 5970.9262 | G106: =IF((G105*G90)<0,0,(G105*G90)) -> 6382.9201 | H106: =IF((H105*H90)<0,0,(H105*H90)) -> 6823.3416 | I106: =IF((I105*I90)<0,0,(I105*I90)) -> 7294.1522 | J106: =IF((J105*J90)<0,0,(J105*J90)) -> 7797.4487 | K106: =IF((K105*K90)<0,0,(K105*K90)) -> 8335.4727 | ... M106: =IF((M105*M90)<0,0,(M105*M90)) -> 9525.4531 | AI106: =SUM(D106:N106) -> 71850.86 | AJ106: =AI106/AI108 -> 1
B108: income needed inclusive of fees | D108: =IF(D85<=$C$5,(D102+D106),0) -> 5225 | E108: =IF(E85<=$C$5,(E102+E106),0) -> 5585.525 | F108: =IF(F85<=$C$5,(F102+F106),0) -> 5970.9262 | G108: =IF(G85<=$C$5,(G102+G106),0) -> 6382.9201 | H108: =IF(H85<=$C$5,(H102+H106),0) -> 6823.3416 | I108: =IF(I85<=$C$5,(I102+I106),0) -> 7294.1522 | J108: =IF(J85<=$C$5,(J102+J106),0) -> 7797.4487 | K108: =IF(K85<=$C$5,(K102+K106),0) -> 8335.4727 | ... M108: =IF(M85<=$C$5,(M102+M106),0) -> 9525.4531 | AI108: =SUM(D108:N108) -> 71850.86
B110: Finial Closing balance | D110: =D100-D102 -> 513000 | E110: =E100-E102 -> 548397 | F110: =F100-F102 -> 586236.39 | G110: =G100-G102 -> 626686.7 | H110: =H100-H102 -> 669928.09 | I110: =I100-I102 -> 716153.12 | J110: =J100-J102 -> 765567.69 | K110: =K100-K102 -> 818391.86 | ... M110: =M100-M102 -> 935226.3

Sheet Carvan
B1: Caravan
B2: Calander Year at Stage | C2: ='Income - Stage 1'!C3 -> 2026
B3: Start year | C3: ='Income - Stage 1'!C4 -> 1
B4: Stage length | C4: 19
B5: Finish Year | C5: =C2+C4 -> 2045
B6: The year that needs to be iqual to $0 is | C6: =C5+1 -> 2046
B8: Partner 1 age at start of Stage | C8: ='Income - Stage 1'!C7 -> 65
B9: Partner 1 age at END of Stage | C9: =C8+C4 -> 84
B11: Partner 2 age at stage of stage | C11: ='Income - Stage 1'!C8 -> 62
B12: Partner 2 age at END of Stage | C12: =C11+C4 -> 81
B14: Tax Rate (%) | C14: 0
B15: Fees % | C15: 0.011
B16: Inflation | C16: 0.03
B18: Portfolio | C18: Balanced | D18: "- this is a pull down menue that automatically fills in the Income % and Growth %"
B19: Portfolio Attributes
B20: income return (%) | C20: 0.035
B21: Growth (%) | C21: 0.045
B23: Calander Year | D23: =C2 -> 2026 | E23: =D23+1 -> 2027 | F23: =E23+1 -> 2028 | G23: =F23+1 -> 2029 | H23: =G23+1 -> 2030 | I23: =H23+1 -> 2031 | J23: =I23+1 -> 2032 | K23: =J23+1 -> 2033 | L23: =K23+1 -> 2034 | ... AI23: =AH23+1 -> 2057
B24: Year | D24: =C3 -> 1 | E24: =D24+1 -> 2 | F24: =E24+1 -> 3 | G24: =F24+1 -> 4 | H24: =G24+1 -> 5 | I24: =H24+1 -> 6 | J24: =I24+1 -> 7 | K24: =J24+1 -> 8 | L24: =K24+1 -> 9 | ... AI24: =AH24+1 -> 32
B25: Partner 1 age | D25: =C8 -> 65 | E25: =D25+1 -> 66 | F25: =E25+1 -> 67 | G25: =F25+1 -> 68 | H25: =G25+1 -> 69 | I25: =H25+1 -> 70 | J25: =I25+1 -> 71 | K25: =J25+1 -> 72 | L25: =K25+1 -> 73 | ... AI25: =AH25+1 -> 96
B26: Partner 2 age | D26: =C11 -> 62 | E26: =D26+1 -> 63 | F26: =E26+1 -> 64 | G26: =F26+1 -> 65 | H26: =G26+1 -> 66 | I26: =H26+1 -> 67 | J26: =I26+1 -> 68 | K26: =J26+1 -> 69 | L26: =K26+1 -> 70 | ... AI26: =AH26+1 -> 93
B29: open balance | D29: 88801.295 | E29: =D58 -> 14405.399 | F29: =E58 -> 14057.831 | G29: =F58 -> 13682.457 | H29: =G58 -> 13277.054 | I29: =H58 -> 12839.218 | J29: =I58 -> 12366.355 | K29: =J58 -> 11855.664 | L29: =K58 -> 11304.117 | ... AI29: =AH58 -> -9.5496944e-12
B30: income return (%) | D30: =C20 -> 0.035 | E30: =D30 -> 0.035 | F30: =E30 -> 0.035 | G30: =F30 -> 0.035 | H30: =G30 -> 0.035 | I30: =H30 -> 0.035 | J30: =I30 -> 0.035 | K30: =J30 -> 0.035 | L30: =K30 -> 0.035 | ... AI30: =AH30 -> 0.035
B31: income return ($) | D31: =D29*D30 -> 3108.0453 | E31: =E29*E30 -> 504.18896 | F31: =F29*F30 -> 492.02407 | G31: =G29*G30 -> 478.886 | H31: =H29*H30 -> 464.69688 | I31: =I29*I30 -> 449.37263 | J31: =J29*J30 -> 432.82244 | K31: =K29*K30 -> 414.94824 | ... AI31: =AI29*AI30 -> -3.342393e-13
B32: Tax Rate (%) | D32: =C14 -> 0 | E32: =D32 -> 0 | F32: =E32 -> 0 | G32: =F32 -> 0 | H32: =G32 -> 0 | I32: =H32 -> 0 | J32: =I32 -> 0 | K32: =J32 -> 0 | L32: =K32 -> 0 | ... AI32: =AH32 -> 0
B33: Tax Rate ($) | D33: =IF((D31*D32)<0,0,(D31*D32)) -> 0 | E33: =IF((E31*E32)<0,0,(E31*E32)) -> 0 | F33: =IF((F31*F32)<0,0,(F31*F32)) -> 0 | G33: =IF((G31*G32)<0,0,(G31*G32)) -> 0 | H33: =IF((H31*H32)<0,0,(H31*H32)) -> 0 | I33: =IF((I31*I32)<0,0,(I31*I32)) -> 0 | J33: =IF((J31*J32)<0,0,(J31*J32)) -> 0 | K33: =IF((K31*K32)<0,0,(K31*K32)) -> 0 | ... AI33: =IF((AI31*AI32)<0,0,(AI31*AI32)) -> 0
B34: Income after tax | D34: =IF((D31-D33)<0,0,(D31-D33)) -> 3108.0453 | E34: =IF((E31-E33)<0,0,(E31-E33)) -> 504.18896 | F34: =IF((F31-F33)<0,0,(F31-F33)) -> 492.02407 | G34: =IF((G31-G33)<0,0,(G31-G33)) -> 478.886 | H34: =IF((H31-H33)<0,0,(H31-H33)) -> 464.69688 | I34: =IF((I31-I33)<0,0,(I31-I33)) -> 449.37263 | J34: =IF((J31-J33)<0,0,(J31-J33)) -> 432.82244 | K34: =IF((K31-K33)<0,0,(K31-K33)) -> 414.94824 | ... AI34: =IF((AI31-AI33)<0,0,(AI31-AI33)) -> 0
B36: Growth (%) | D36: =C21 -> 0.045 | E36: =D36 -> 0.045 | F36: =E36 -> 0.045 | G36: =F36 -> 0.045 | H36: =G36 -> 0.045 | I36: =H36 -> 0.045 | J36: =I36 -> 0.045 | K36: =J36 -> 0.045 | L36: =K36 -> 0.045 | ... AI36: =AH36 -> 0.045
B37: Growth ($) | D37: =IF((D36*D29)<0,0,(D36*D29)) -> 3996.0583 | E37: =IF((E36*E29)<0,0,(E36*E29)) -> 648.24295 | F37: =IF((F36*F29)<0,0,(F36*F29)) -> 632.60238 | G37: =IF((G36*G29)<0,0,(G36*G29)) -> 615.71057 | H37: =IF((H36*H29)<0,0,(H36*H29)) -> 597.46742 | I37: =IF((I36*I29)<0,0,(I36*I29)) -> 577.76481 | J37: =IF((J36*J29)<0,0,(J36*J29)) -> 556.486 | K37: =IF((K36*K29)<0,0,(K36*K29)) -> 533.50488 | ... AI37: =IF((AI36*AI29)<0,0,(AI36*AI29)) -> 0
B39: Closing Balance | D39: =D29+D34+D37 -> 95905.399 | E39: =E29+E34+E37 -> 15557.831 | F39: =F29+F34+F37 -> 15182.457 | G39: =G29+G34+G37 -> 14777.054 | H39: =H29+H34+H37 -> 14339.218 | I39: =I29+I34+I37 -> 13866.355 | J39: =J29+J34+J37 -> 13355.664 | K39: =K29+K34+K37 -> 12804.117 | ... AI39: =AI29+AI34+AI37 -> -9.5496944e-12
B41: Capital Needed - Purchase Price | D41: 80000 | E41: 0 | F41: 0 | G41: 0 | H41: 0 | I41: 0 | J41: 0 | K41: 0 | L41: 0 | M41: 0 | N41: 0 | O41: 0 | P41: 0 | Q41: 0 | R41: 0 | S41: 0 | T41: 0 | U41: 0 | V41: 0 | W41: 0 | X41: 0 | Y41: 0 | Z41: 0 | AA41: 0 | AB41: 0 | AC41: 0 | AD41: 0 | AE41: 0 | AF41: 0 | AG41: 0 | AH41: 0 | AI41: 0
B42: Trade in Value | D42: 0 | M42: 0 | V42: 0 | AC42: 0
B43: Holding Cost
B44: Rego | C44: 200
B45: Insurance | C45: 800
B46: Maintenance | C46: 300
B47: Services | C47: 200
B48: Hollding Costs - Total | C48: =SUM(C44:C47) -> 1500 | D48: =IF(D23<$C$6,C48,0) -> 1500 | E48: =IF(E23<$C$6,D48,0) -> 1500 | F48: =IF(F23<$C$6,E48,0) -> 1500 | G48: =IF(G23<$C$6,F48,0) -> 1500 | H48: =IF(H23<$C$6,G48,0) -> 1500 | I48: =IF(I23<$C$6,H48,0) -> 1500 | J48: =IF(J23<$C$6,I48,0) -> 1500 | K48: =IF(K23<$C$6,J48,0) -> 1500 | ... AI48: =IF(AI23<$C$6,AH48,0) -> 0
B50: income needed ex fees | D50: =D41-D42+D48 -> 81500 | E50: =E41-E42+E48 -> 1500 | F50: =F41-F42+F48 -> 1500 | G50: =G41-G42+G48 -> 1500 | H50: =H41-H42+H48 -> 1500 | I50: =I41-I42+I48 -> 1500 | J50: =J41-J42+J48 -> 1500 | K50: =K41-K42+K48 -> 1500 | ... AI50: =AI41-AI42+AI48 -> 0
B51: Inflation assumed | D51: =C16 -> 0.03 | E51: =D51 -> 0.03 | F51: =E51 -> 0.03 | G51: =F51 -> 0.03 | H51: =G51 -> 0.03 | I51: =H51 -> 0.03 | J51: =I51 -> 0.03 | K51: =J51 -> 0.03 | L51: =K51 -> 0.03 | ... AI51: =AH51 -> 0.03
B53: Fees (%) | D53: =C15 -> 0.011 | E53: =D53 -> 0.011 | F53: =E53 -> 0.011 | G53: =F53 -> 0.011 | H53: =G53 -> 0.011 | I53: =H53 -> 0.011 | J53: =I53 -> 0.011 | K53: =J53 -> 0.011 | L53: =K53 -> 0.011 | ... AI53: =AH53 -> 0.011
B54: Fees ($) | D54: =IF((D53*D29)<0,0,(D53*D29)) -> 976.81425 | E54: =IF((E53*E29)<0,0,(E53*E29)) -> 158.45939 | F54: =IF((F53*F29)<0,0,(F53*F29)) -> 154.63614 | G54: =IF((G53*G29)<0,0,(G53*G29)) -> 150.50703 | H54: =IF((H53*H29)<0,0,(H53*H29)) -> 146.04759 | I54: =IF((I53*I29)<0,0,(I53*I29)) -> 141.2314 | J54: =IF((J53*J29)<0,0,(J53*J29)) -> 136.02991 | K54: =IF((K53*K29)<0,0,(K53*K29)) -> 130.4123 | ... AI54: =IF((AI53*AI29)<0,0,(AI53*AI29)) -> 0 | AJ54: =AI54/AI56 -> #DIV/0!
B56: income needed inclusive of fees | D56: =IF(D23<=$C$60,(D50+D54),0) -> 0 | E56: =IF(E23<=$C$60,(E50+E54),0) -> 0 | F56: =IF(F23<=$C$60,(F50+F54),0) -> 0 | G56: =IF(G23<=$C$60,(G50+G54),0) -> 0 | H56: =IF(H23<=$C$60,(H50+H54),0) -> 0 | I56: =IF(I23<=$C$60,(I50+I54),0) -> 0 | J56: =IF(J23<=$C$60,(J50+J54),0) -> 0 | K56: =IF(K23<=$C$60,(K50+K54),0) -> 0 | ... AI56: =IF(AI23<=$C$60,(AI50+AI54),0) -> 0
B58: Finial Closing balance | D58: =D39-D50 -> 14405.399 | E58: =E39-E50 -> 14057.831 | F58: =F39-F50 -> 13682.457 | G58: =G39-G50 -> 13277.054 | H58: =H39-H50 -> 12839.218 | I58: =I39-I50 -> 12366.355 | J58: =J39-J50 -> 11855.664 | K58: =K39-K50 -> 11304.117 | ... AI58: =AI39-AI50 -> -9.5496944e-12
B60: if by | D60: =D23 -> 2026
B61: I need | D61: =D29 -> 88801.295 | E61: in capital
B62: Assuming
B63: Portfolio | D63: Balanced | E63: "- this is a pull down menue that automatically fills in the Income % and Growth %"
B64: Portfolio Attributes
B65: income return (%) | D65: 0.035
B66: Growth (%) | D66: 0.045
B68: Stage 2 Funding at beging of Stage 1
B69: Calander Year at Stage | C69: 2026
B70: Start year | C70: 1
B71: Stage length | C71: 5
B72: Finish Year | C72: =C69+C71 -> 2031
B73: Partner 1 age | C73: 65
B74: Partner 2 age | C74: 62
B75: Tax Rate (%) | C75: 0
B76: Fees % | C76: 0.011
B77: Inflation | C77: 0.03
B79: Portfolio | C79: =C18 -> Balanced | D79: "- this is a pull down menue that automatically fills in the Income % and Growth %"
B80: Portfolio Attributes
B81: income return (%) | C81: =C20 -> 0.035
B82: Growth (%) | C82: =C21 -> 0.045
B84: Calander Year | D84: =C69 -> 2026 | E84: =D84+1 -> 2027 | F84: =E84+1 -> 2028 | G84: =F84+1 -> 2029 | H84: =G84+1 -> 2030 | I84: =H84+1 -> 2031 | J84: =I84+1 -> 2032 | K84: =J84+1 -> 2033 | L84: =K84+1 -> 2034 | M84: =L84+1 -> 2035
B85: Year | D85: 0 | E85: =D85+1 -> 1 | F85: =E85+1 -> 2 | G85: =F85+1 -> 3 | H85: =G85+1 -> 4 | I85: =H85+1 -> 5 | J85: =I85+1 -> 6 | K85: =J85+1 -> 7 | L85: =K85+1 -> 8 | M85: =L85+1 -> 9
B86: Partner 1 age | D86: =C73 -> 65 | E86: =D86+1 -> 66 | F86: =E86+1 -> 67 | G86: =F86+1 -> 68 | H86: =G86+1 -> 69 | I86: =H86+1 -> 70 | J86: =I86+1 -> 71 | K86: =J86+1 -> 72 | L86: =K86+1 -> 73 | M86: =L86+1 -> 74
B87: Partner 2 age | D87: =C74 -> 62 | E87: =D87+1 -> 63 | F87: =E87+1 -> 64 | G87: =F87+1 -> 65 | H87: =G87+1 -> 66 | I87: =H87+1 -> 67 | J87: =I87+1 -> 68 | K87: =J87+1 -> 69 | L87: =K87+1 -> 70 | M87: =L87+1 -> 71
B90: open balance | D90: 475000 | E90: =D100-D108 -> 507775 | F90: =E100-E108 -> 542811.47 | G90: =F100-F108 -> 580265.47 | H90: =G100-G108 -> 620303.78 | I90: =H100-H108 -> 663104.75 | J90: =I100-I108 -> 708858.97 | K90: =J100-J108 -> 757770.24 | L90: =K100-K108 -> 810056.39 | M90: =L100-L108 -> 865950.28
B91: income return (%) | D91: =C81 -> 0.035 | E91: =D91 -> 0.035 | F91: =E91 -> 0.035 | G91: =F91 -> 0.035 | H91: =G91 -> 0.035 | I91: =H91 -> 0.035 | J91: =I91 -> 0.035 | K91: =J91 -> 0.035 | L91: =K91 -> 0.035 | M91: =L91 -> 0.035
B92: income return ($) | D92: =D90*D91 -> 16625 | E92: =E90*E91 -> 17772.125 | F92: =F90*F91 -> 18998.402 | G92: =G90*G91 -> 20309.291 | H92: =H90*H91 -> 21710.632 | I92: =I90*I91 -> 23208.666 | J92: =J90*J91 -> 24810.064 | K92: =K90*K91 -> 26521.958 | ... M92: =M90*M91 -> 30308.26
B93: Tax Rate (%) | D93: =C75 -> 0 | E93: =D93 -> 0 | F93: =E93 -> 0 | G93: =F93 -> 0 | H93: =G93 -> 0 | I93: =H93 -> 0 | J93: =I93 -> 0 | K93: =J93 -> 0 | L93: =K93 -> 0 | M93: =L93 -> 0
B94: Tax Rate ($) | D94: =IF((D92*D93)<0,0,(D92*D93)) -> 0 | E94: =IF((E92*E93)<0,0,(E92*E93)) -> 0 | F94: =IF((F92*F93)<0,0,(F92*F93)) -> 0 | G94: =IF((G92*G93)<0,0,(G92*G93)) -> 0 | H94: =IF((H92*H93)<0,0,(H92*H93)) -> 0 | I94: =IF((I92*I93)<0,0,(I92*I93)) -> 0 | J94: =IF((J92*J93)<0,0,(J92*J93)) -> 0 | K94: =IF((K92*K93)<0,0,(K92*K93)) -> 0 | ... M94: =IF((M92*M93)<0,0,(M92*M93)) -> 0 | AI94: =SUM(D94:N94) -> 0
B95: Income after tax | D95: =IF((D92-D94)<0,0,(D92-D94)) -> 16625 | E95: =IF((E92-E94)<0,0,(E92-E94)) -> 17772.125 | F95: =IF((F92-F94)<0,0,(F92-F94)) -> 18998.402 | G95: =IF((G92-G94)<0,0,(G92-G94)) -> 20309.291 | H95: =IF((H92-H94)<0,0,(H92-H94)) -> 21710.632 | I95: =IF((I92-I94)<0,0,(I92-I94)) -> 23208.666 | J95: =IF((J92-J94)<0,0,(J92-J94)) -> 24810.064 | K95: =IF((K92-K94)<0,0,(K92-K94)) -> 26521.958 | ... M95: =IF((M92-M94)<0,0,(M92-M94)) -> 30308.26 | AI95: =SUM(D95:N95) -> 228616.37
B97: Growth (%) | D97: =C82 -> 0.045 | E97: =D97 -> 0.045 | F97: =E97 -> 0.045 | G97: =F97 -> 0.045 | H97: =G97 -> 0.045 | I97: =H97 -> 0.045 | J97: =I97 -> 0.045 | K97: =J97 -> 0.045 | L97: =K97 -> 0.045 | M97: =L97 -> 0.045
B98: Growth ($) | D98: =IF((D97*D90)<0,0,(D97*D90)) -> 21375 | E98: =IF((E97*E90)<0,0,(E97*E90)) -> 22849.875 | F98: =IF((F97*F90)<0,0,(F97*F90)) -> 24426.516 | G98: =IF((G97*G90)<0,0,(G97*G90)) -> 26111.946 | H98: =IF((H97*H90)<0,0,(H97*H90)) -> 27913.67 | I98: =IF((I97*I90)<0,0,(I97*I90)) -> 29839.714 | J98: =IF((J97*J90)<0,0,(J97*J90)) -> 31898.654 | K98: =IF((K97*K90)<0,0,(K97*K90)) -> 34099.661 | ... M98: =IF((M97*M90)<0,0,(M97*M90)) -> 38967.763 | AI98: =SUM(D98:M98) -> 293935.34
B100: Closing Balance | D100: =D90+D95+D98 -> 513000 | E100: =E90+E95+E98 -> 548397 | F100: =F90+F95+F98 -> 586236.39 | G100: =G90+G95+G98 -> 626686.7 | H100: =H90+H95+H98 -> 669928.09 | I100: =I90+I95+I98 -> 716153.12 | J100: =J90+J95+J98 -> 765567.69 | K100: =K90+K95+K98 -> 818391.86 | ... M100: =M90+M95+M98 -> 935226.3
B102: income needed ex fees | D102: 0 | E102: =D102*(1+D103) -> 0 | F102: =E102*(1+E103) -> 0 | G102: =F102*(1+F103) -> 0 | H102: =G102*(1+G103) -> 0 | I102: =H102*(1+H103) -> 0 | J102: =I102*(1+I103) -> 0 | K102: =J102*(1+J103) -> 0 | L102: =K102*(1+K103) -> 0 | M102: =L102*(1+L103) -> 0
B103: Inflation assumed | D103: =C77 -> 0.03 | E103: =D103 -> 0.03 | F103: =E103 -> 0.03 | G103: =F103 -> 0.03 | H103: =G103 -> 0.03 | I103: =H103 -> 0.03 | J103: =I103 -> 0.03 | K103: =J103 -> 0.03 | L103: =K103 -> 0.03 | M103: =L103 -> 0.03
B105: Fees (%) | D105: =C76 -> 0.011 | E105: =D105 -> 0.011 | F105: =E105 -> 0.011 | G105: =F105 -> 0.011 | H105: =G105 -> 0.011 | I105: =H105 -> 0.011 | J105: =I105 -> 0.011 | K105: =J105 -> 0.011 | L105: =K105 -> 0.011 | M105: =L105 -> 0.011
B106: Fees ($) | D106: =IF((D105*D90)<0,0,(D105*D90)) -> 5225 | E106: =IF((E105*E90)<0,0,(E105*E90)) -> 5585.525 | F106: =IF((F105*F90)<0,0,(F105*F90)) -> 5970.9262 | G106: =IF((G105*G90)<0,0,(G105*G90)) -> 6382.9201 | H106: =IF((H105*H90)<0,0,(H105*H90)) -> 6823.3416 | I106: =IF((I105*I90)<0,0,(I105*I90)) -> 7294.1522 | J106: =IF((J105*J90)<0,0,(J105*J90)) -> 7797.4487 | K106: =IF((K105*K90)<0,0,(K105*K90)) -> 8335.4727 | ... M106: =IF((M105*M90)<0,0,(M105*M90)) -> 9525.4531 | AI106: =SUM(D106:N106) -> 71850.86 | AJ106: =AI106/AI108 -> 1
B108: income needed inclusive of fees | D108: =IF(D85<=$C$5,(D102+D106),0) -> 5225 | E108: =IF(E85<=$C$5,(E102+E106),0) -> 5585.525 | F108: =IF(F85<=$C$5,(F102+F106),0) -> 5970.9262 | G108: =IF(G85<=$C$5,(G102+G106),0) -> 6382.9201 | H108: =IF(H85<=$C$5,(H102+H106),0) -> 6823.3416 | I108: =IF(I85<=$C$5,(I102+I106),0) -> 7294.1522 | J108: =IF(J85<=$C$5,(J102+J106),0) -> 7797.4487 | K108: =IF(K85<=$C$5,(K102+K106),0) -> 8335.4727 | ... M108: =IF(M85<=$C$5,(M102+M106),0) -> 9525.4531 | AI108: =SUM(D108:N108) -> 71850.86
B110: Finial Closing balance | D110: =D100-D102 -> 513000 | E110: =E100-E102 -> 548397 | F110: =F100-F102 -> 586236.39 | G110: =G100-G102 -> 626686.7 | H110: =H100-H102 -> 669928.09 | I110: =I100-I102 -> 716153.12 | J110: =J100-J102 -> 765567.69 | K110: =K100-K102 -> 818391.86 | ... M110: =M100-M102 -> 935226.3

Sheet Boat

Sheet Domestic Holidays
B1: Car for Partner 2
B2: Calander Year at Stage | C2: ='Income - Stage 1'!C3 -> 2026
B3: Start year | C3: ='Income - Stage 1'!C4 -> 1
B4: Stage length | C4: 23
B5: Finish Year | C5: =C2+C4 -> 2049
B6: The year that needs to be iqual to $0 is | C6: =C5+1 -> 2050
B8: Partner 1 age at start of Stage | C8: ='Income - Stage 1'!C7 -> 65
B9: Partner 1 age at END of Stage | C9: =C8+C4 -> 88
B11: Partner 2 age at stage of stage | C11: ='Income - Stage 1'!C8 -> 62
B12: Partner 2 age at END of Stage | C12: =C11+C4 -> 85
B14: Tax Rate (%) | C14: 0.15
B15: Fees % | C15: 0.011
B16: Inflation | C16: 0.03
B18: Portfolio | C18: Balanced | D18: "- this is a pull down menue that automatically fills in the Income % and Growth %"
B19: Portfolio Attributes
B20: income return (%) | C20: 0.035
B21: Growth (%) | C21: 0.045
B23: Calander Year | D23: =C2 -> 2026 | E23: =D23+1 -> 2027 | F23: =E23+1 -> 2028 | G23: =F23+1 -> 2029 | H23: =G23+1 -> 2030 | I23: =H23+1 -> 2031 | J23: =I23+1 -> 2032 | K23: =J23+1 -> 2033 | L23: =K23+1 -> 2034 | ... AI23: =AH23+1 -> 2057
B24: Year | D24: =C3 -> 1 | E24: =D24+1 -> 2 | F24: =E24+1 -> 3 | G24: =F24+1 -> 4 | H24: =G24+1 -> 5 | I24: =H24+1 -> 6 | J24: =I24+1 -> 7 | K24: =J24+1 -> 8 | L24: =K24+1 -> 9 | ... AI24: =AH24+1 -> 32
B25: Partner 1 age | D25: =C8 -> 65 | E25: =D25+1 -> 66 | F25: =E25+1 -> 67 | G25: =F25+1 -> 68 | H25: =G25+1 -> 69 | I25: =H25+1 -> 70 | J25: =I25+1 -> 71 | K25: =J25+1 -> 72 | L25: =K25+1 -> 73 | ... AI25: =AH25+1 -> 96
B26: Partner 2 age | D26: =C11 -> 62 | E26: =D26+1 -> 63 | F26: =E26+1 -> 64 | G26: =F26+1 -> 65 | H26: =G26+1 -> 66 | I26: =H26+1 -> 67 | J26: =I26+1 -> 68 | K26: =J26+1 -> 69 | L26: =K26+1 -> 70 | ... AI26: =AH26+1 -> 93
B29: open balance | D29: 115568.24 | E29: =D56 -> 113706.96 | F29: =E56 -> 111706.56 | G29: =F56 -> 109556.62 | H29: =G56 -> 107245.98 | I29: =H56 -> 104762.62 | J29: =I56 -> 102093.62 | K29: =J56 -> 99225.119 | L29: =K56 -> 96142.197 | ... AI29: =AH56 -> 3.6154603e-11
B30: income return (%) | D30: =C20 -> 0.035 | E30: =D30 -> 0.035 | F30: =E30 -> 0.035 | G30: =F30 -> 0.035 | H30: =G30 -> 0.035 | I30: =H30 -> 0.035 | J30: =I30 -> 0.035 | K30: =J30 -> 0.035 | L30: =K30 -> 0.035 | ... AI30: =AH30 -> 0.035
B31: income return ($) | D31: =D29*D30 -> 4044.8882 | E31: =E29*E30 -> 3979.7436 | F31: =F29*F30 -> 3909.7295 | G31: =G29*G30 -> 3834.4817 | H31: =H29*H30 -> 3753.6093 | I31: =I29*I30 -> 3666.6915 | J31: =J29*J30 -> 3573.2767 | K31: =K29*K30 -> 3472.8792 | ... AI31: =AI29*AI30 -> 1.2654111e-12
B32: Tax Rate (%) | D32: =C14 -> 0.15 | E32: =D32 -> 0.15 | F32: =E32 -> 0.15 | G32: =F32 -> 0.15 | H32: =G32 -> 0.15 | I32: =H32 -> 0.15 | J32: =I32 -> 0.15 | K32: =J32 -> 0.15 | L32: =K32 -> 0.15 | ... AI32: =AH32 -> 0.15
B33: Tax Rate ($) | D33: =IF((D31*D32)<0,0,(D31*D32)) -> 606.73323 | E33: =IF((E31*E32)<0,0,(E31*E32)) -> 596.96154 | F33: =IF((F31*F32)<0,0,(F31*F32)) -> 586.45942 | G33: =IF((G31*G32)<0,0,(G31*G32)) -> 575.17226 | H33: =IF((H31*H32)<0,0,(H31*H32)) -> 563.04139 | I33: =IF((I31*I32)<0,0,(I31*I32)) -> 550.00373 | J33: =IF((J31*J32)<0,0,(J31*J32)) -> 535.99151 | K33: =IF((K31*K32)<0,0,(K31*K32)) -> 520.93188 | ... AI33: =IF((AI31*AI32)<0,0,(AI31*AI32)) -> 1.8981166e-13
B34: Income after tax | D34: =IF((D31-D33)<0,0,(D31-D33)) -> 3438.155 | E34: =IF((E31-E33)<0,0,(E31-E33)) -> 3382.7821 | F34: =IF((F31-F33)<0,0,(F31-F33)) -> 3323.27 | G34: =IF((G31-G33)<0,0,(G31-G33)) -> 3259.3095 | H34: =IF((H31-H33)<0,0,(H31-H33)) -> 3190.5679 | I34: =IF((I31-I33)<0,0,(I31-I33)) -> 3116.6878 | J34: =IF((J31-J33)<0,0,(J31-J33)) -> 3037.2852 | K34: =IF((K31-K33)<0,0,(K31-K33)) -> 2951.9473 | ... AI34: =IF((AI31-AI33)<0,0,(AI31-AI33)) -> 1.0755994e-12
B36: Growth (%) | D36: =C21 -> 0.045 | E36: =D36 -> 0.045 | F36: =E36 -> 0.045 | G36: =F36 -> 0.045 | H36: =G36 -> 0.045 | I36: =H36 -> 0.045 | J36: =I36 -> 0.045 | K36: =J36 -> 0.045 | L36: =K36 -> 0.045 | ... AI36: =AH36 -> 0.045
B37: Growth ($) | D37: =IF((D36*D29)<0,0,(D36*D29)) -> 5200.5706 | E37: =IF((E36*E29)<0,0,(E36*E29)) -> 5116.8132 | F37: =IF((F36*F29)<0,0,(F36*F29)) -> 5026.795 | G37: =IF((G36*G29)<0,0,(G36*G29)) -> 4930.048 | H37: =IF((H36*H29)<0,0,(H36*H29)) -> 4826.069 | I37: =IF((I36*I29)<0,0,(I36*I29)) -> 4714.3177 | J37: =IF((J36*J29)<0,0,(J36*J29)) -> 4594.2129 | K37: =IF((K36*K29)<0,0,(K36*K29)) -> 4465.1304 | ... AI37: =IF((AI36*AI29)<0,0,(AI36*AI29)) -> 1.6269571e-12
B39: Closing Balance | D39: =D29+D34+D37 -> 124206.96 | E39: =E29+E34+E37 -> 122206.56 | F39: =F29+F34+F37 -> 120056.62 | G39: =G29+G34+G37 -> 117745.98 | H39: =H29+H34+H37 -> 115262.62 | I39: =I29+I34+I37 -> 112593.62 | J39: =J29+J34+J37 -> 109725.12 | K39: =K29+K34+K37 -> 106642.2 | ... AI39: =AI29+AI34+AI37 -> 3.8857159e-11
B41: holiday costs
B42: Weeks per year | C42: 2
B43: Days away | C43: =C42*7 -> 14
B45: Accomodation cost per night | C45: 350
B46: Transport cost per day | C46: 100
B47: Food cost per day | C47: 150
B48: Fun cost per day | C48: 150
B49: No of Airfairs | C49: 0
B50: Tickets per person | C50: 0
B52: Hollding Costs - Total | C52: =(C43*(C45+C46+C47+C48)+(C49*C50)) -> 10500
B53: Frequence of years between trips | C53: 1
B54: Hollding Costs - Total | C54: =C52/C53 -> 10500 | D54: =IF(D23<$C$6,C54,0) -> 10500 | E54: =IF(E23<$C$6,D54,0) -> 10500 | F54: =IF(F23<$C$6,E54,0) -> 10500 | G54: =IF(G23<$C$6,F54,0) -> 10500 | H54: =IF(H23<$C$6,G54,0) -> 10500 | I54: =IF(I23<$C$6,H54,0) -> 10500 | J54: =IF(J23<$C$6,I54,0) -> 10500 | K54: =IF(K23<$C$6,J54,0) -> 10500 | ... AI54: =IF(AI23<$C$6,AH54,0) -> 0
B56: income needed ex fees | D56: =D39-D54 -> 113706.96 | E56: =E39-E54 -> 111706.56 | F56: =F39-F54 -> 109556.62 | G56: =G39-G54 -> 107245.98 | H56: =H39-H54 -> 104762.62 | I56: =I39-I54 -> 102093.62 | J56: =J39-J54 -> 99225.119 | K56: =K39-K54 -> 96142.197 | ... AI56: =AI39-AI54 -> 3.8857159e-11
B57: Inflation assumed | D57: =C16 -> 0.03 | E57: =D57 -> 0.03 | F57: =E57 -> 0.03 | G57: =F57 -> 0.03 | H57: =G57 -> 0.03 | I57: =H57 -> 0.03 | J57: =I57 -> 0.03 | K57: =J57 -> 0.03 | L57: =K57 -> 0.03 | ... AI57: =AH57 -> 0.03
B59: Fees (%) | D59: =C15 -> 0.011 | E59: =D59 -> 0.011 | F59: =E59 -> 0.011 | G59: =F59 -> 0.011 | H59: =G59 -> 0.011 | I59: =H59 -> 0.011 | J59: =I59 -> 0.011 | K59: =J59 -> 0.011 | L59: =K59 -> 0.011 | ... AI59: =AH59 -> 0.011
B60: Fees ($) | D60: =IF((D59*D29)<0,0,(D59*D29)) -> 1271.2506 | E60: =IF((E59*E29)<0,0,(E59*E29)) -> 1250.7766 | F60: =IF((F59*F29)<0,0,(F59*F29)) -> 1228.7721 | G60: =IF((G59*G29)<0,0,(G59*G29)) -> 1205.1228 | H60: =IF((H59*H29)<0,0,(H59*H29)) -> 1179.7058 | I60: =IF((I59*I29)<0,0,(I59*I29)) -> 1152.3888 | J60: =IF((J59*J29)<0,0,(J59*J29)) -> 1123.0298 | K60: =IF((K59*K29)<0,0,(K59*K29)) -> 1091.4763 | ... AI60: =IF((AI59*AI29)<0,0,(AI59*AI29)) -> 3.9770063e-13 | AJ60: =AI60/AI62 -> #DIV/0!
B62: income needed inclusive of fees | D62: =IF(D23<=$C$66,(D56+D60),0) -> 0 | E62: =IF(E23<=$C$66,(E56+E60),0) -> 0 | F62: =IF(F23<=$C$66,(F56+F60),0) -> 0 | G62: =IF(G23<=$C$66,(G56+G60),0) -> 0 | H62: =IF(H23<=$C$66,(H56+H60),0) -> 0 | I62: =IF(I23<=$C$66,(I56+I60),0) -> 0 | J62: =IF(J23<=$C$66,(J56+J60),0) -> 0 | K62: =IF(K23<=$C$66,(K56+K60),0) -> 0 | ... AI62: =IF(AI23<=$C$66,(AI56+AI60),0) -> 0
B64: Finial Closing balance | D64: =D39-D56 -> 10500 | E64: =E39-E56 -> 10500 | F64: =F39-F56 -> 10500 | G64: =G39-G56 -> 10500 | H64: =H39-H56 -> 10500 | I64: =I39-I56 -> 10500 | J64: =J39-J56 -> 10500 | K64: =K39-K56 -> 10500 | ... AI64: =AI39-AI56 -> 0
B66: if by | D66: =D23 -> 2026
B67: I need | D67: =D29 -> 115568.24 | E67: in capital
B68: Assuming
B69: Portfolio | D69: Balanced | E69: "- this is a pull down menue that automatically fills in the Income % and Growth %"
B70: Portfolio Attributes
B71: income return (%) | D71: 0.035
B72: Growth (%) | D72: 0.045
B74: Stage 2 Funding at beging of Stage 1
B75: Calander Year at Stage | C75: 2026
B76: Start year | C76: 1
B77: Stage length | C77: 5
B78: Finish Year | C78: =C75+C77 -> 2031
B79: Partner 1 age | C79: 65
B80: Partner 2 age | C80: 62
B81: Tax Rate (%) | C81: 0
B82: Fees % | C82: 0.011
B83: Inflation | C83: 0.03
B85: Portfolio | C85: =C18 -> Balanced | D85: "- this is a pull down menue that automatically fills in the Income % and Growth %"
B86: Portfolio Attributes
B87: income return (%) | C87: =C20 -> 0.035
B88: Growth (%) | C88: =C21 -> 0.045
B90: Calander Year | D90: =C75 -> 2026 | E90: =D90+1 -> 2027 | F90: =E90+1 -> 2028 | G90: =F90+1 -> 2029 | H90: =G90+1 -> 2030 | I90: =H90+1 -> 2031 | J90: =I90+1 -> 2032 | K90: =J90+1 -> 2033 | L90: =K90+1 -> 2034 | M90: =L90+1 -> 2035
B91: Year | D91: 0 | E91: =D91+1 -> 1 | F91: =E91+1 -> 2 | G91: =F91+1 -> 3 | H91: =G91+1 -> 4 | I91: =H91+1 -> 5 | J91: =I91+1 -> 6 | K91: =J91+1 -> 7 | L91: =K91+1 -> 8 | M91: =L91+1 -> 9
B92: Partner 1 age | D92: =C79 -> 65 | E92: =D92+1 -> 66 | F92: =E92+1 -> 67 | G92: =F92+1 -> 68 | H92: =G92+1 -> 69 | I92: =H92+1 -> 70 | J92: =I92+1 -> 71 | K92: =J92+1 -> 72 | L92: =K92+1 -> 73 | M92: =L92+1 -> 74
B93: Partner 2 age | D93: =C80 -> 62 | E93: =D93+1 -> 63 | F93: =E93+1 -> 64 | G93: =F93+1 -> 65 | H93: =G93+1 -> 66 | I93: =H93+1 -> 67 | J93: =I93+1 -> 68 | K93: =J93+1 -> 69 | L93: =K93+1 -> 70 | M93: =L93+1 -> 71
B96: open balance | D96: 475000 | E96: =D106-D114 -> 507775 | F96: =E106-E114 -> 542811.47 | G96: =F106-F114 -> 580265.47 | H96: =G106-G114 -> 620303.78 | I96: =H106-H114 -> 663104.75 | J96: =I106-I114 -> 708858.97 | K96: =J106-J114 -> 757770.24 | L96: =K106-K114 -> 810056.39 | M96: =L106-L114 -> 865950.28
B97: income return (%) | D97: =C87 -> 0.035 | E97: =D97 -> 0.035 | F97: =E97 -> 0.035 | G97: =F97 -> 0.035 | H97: =G97 -> 0.035 | I97: =H97 -> 0.035 | J97: =I97 -> 0.035 | K97: =J97 -> 0.035 | L97: =K97 -> 0.035 | M97: =L97 -> 0.035
B98: income return ($) | D98: =D96*D97 -> 16625 | E98: =E96*E97 -> 17772.125 | F98: =F96*F97 -> 18998.402 | G98: =G96*G97 -> 20309.291 | H98: =H96*H97 -> 21710.632 | I98: =I96*I97 -> 23208.666 | J98: =J96*J97 -> 24810.064 | K98: =K96*K97 -> 26521.958 | ... M98: =M96*M97 -> 30308.26
B99: Tax Rate (%) | D99: =C81 -> 0 | E99: =D99 -> 0 | F99: =E99 -> 0 | G99: =F99 -> 0 | H99: =G99 -> 0 | I99: =H99 -> 0 | J99: =I99 -> 0 | K99: =J99 -> 0 | L99: =K99 -> 0 | M99: =L99 -> 0
B100: Tax Rate ($) | D100: =IF((D98*D99)<0,0,(D98*D99)) -> 0 | E100: =IF((E98*E99)<0,0,(E98*E99)) -> 0 | F100: =IF((F98*F99)<0,0,(F98*F99)) -> 0 | G100: =IF((G98*G99)<0,0,(G98*G99)) -> 0 | H100: =IF((H98*H99)<0,0,(H98*H99)) -> 0 | I100: =IF((I98*I99)<0,0,(I98*I99)) -> 0 | J100: =IF((J98*J99)<0,0,(J98*J99)) -> 0 | K100: =IF((K98*K99)<0,0,(K98*K99)) -> 0 | ... M100: =IF((M98*M99)<0,0,(M98*M99)) -> 0 | AI100: =SUM(D100:N100) -> 0
B101: Income after tax | D101: =IF((D98-D100)<0,0,(D98-D100)) -> 16625 | E101: =IF((E98-E100)<0,0,(E98-E100)) -> 17772.125 | F101: =IF((F98-F100)<0,0,(F98-F100)) -> 18998.402 | G101: =IF((G98-G100)<0,0,(G98-G100)) -> 20309.291 | H101: =IF((H98-H100)<0,0,(H98-H100)) -> 21710.632 | I101: =IF((I98-I100)<0,0,(I98-I100)) -> 23208.666 | J101: =IF((J98-J100)<0,0,(J98-J100)) -> 24810.064 | K101: =IF((K98-K100)<0,0,(K98-K100)) -> 26521.958 | ... M101: =IF((M98-M100)<0,0,(M98-M100)) -> 30308.26 | AI101: =SUM(D101:N101) -> 228616.37
B103: Growth (%) | D103: =C88 -> 0.045 | E103: =D103 -> 0.045 | F103: =E103 -> 0.045 | G103: =F103 -> 0.045 | H103: =G103 -> 0.045 | I103: =H103 -> 0.045 | J103: =I103 -> 0.045 | K103: =J103 -> 0.045 | L103: =K103 -> 0.045 | M103: =L103 -> 0.045
B104: Growth ($) | D104: =IF((D103*D96)<0,0,(D103*D96)) -> 21375 | E104: =IF((E103*E96)<0,0,(E103*E96)) -> 22849.875 | F104: =IF((F103*F96)<0,0,(F103*F96)) -> 24426.516 | G104: =IF((G103*G96)<0,0,(G103*G96)) -> 26111.946 | H104: =IF((H103*H96)<0,0,(H103*H96)) -> 27913.67 | I104: =IF((I103*I96)<0,0,(I103*I96)) -> 29839.714 | J104: =IF((J103*J96)<0,0,(J103*J96)) -> 31898.654 | K104: =IF((K103*K96)<0,0,(K103*K96)) -> 34099.661 | ... M104: =IF((M103*M96)<0,0,(M103*M96)) -> 38967.763 | AI104: =SUM(D104:M104) -> 293935.34
B106: Closing Balance | D106: =D96+D101+D104 -> 513000 | E106: =E96+E101+E104 -> 548397 | F106: =F96+F101+F104 -> 586236.39 | G106: =G96+G101+G104 -> 626686.7 | H106: =H96+H101+H104 -> 669928.09 | I106: =I96+I101+I104 -> 716153.12 | J106: =J96+J101+J104 -> 765567.69 | K106: =K96+K101+K104 -> 818391.86 | ... M106: =M96+M101+M104 -> 935226.3
B108: income needed ex fees | D108: 0 | E108: =D108*(1+D109) -> 0 | F108: =E108*(1+E109) -> 0 | G108: =F108*(1+F109) -> 0 | H108: =G108*(1+G109) -> 0 | I108: =H108*(1+H109) -> 0 | J108: =I108*(1+I109) -> 0 | K108: =J108*(1+J109) -> 0 | L108: =K108*(1+K109) -> 0 | M108: =L108*(1+L109) -> 0
B109: Inflation assumed | D109: =C83 -> 0.03 | E109: =D109 -> 0.03 | F109: =E109 -> 0.03 | G109: =F109 -> 0.03 | H109: =G109 -> 0.03 | I109: =H109 -> 0.03 | J109: =I109 -> 0.03 | K109: =J109 -> 0.03 | L109: =K109 -> 0.03 | M109: =L109 -> 0.03
B111: Fees (%) | D111: =C82 -> 0.011 | E111: =D111 -> 0.011 | F111: =E111 -> 0.011 | G111: =F111 -> 0.011 | H111: =G111 -> 0.011 | I111: =H111 -> 0.011 | J111: =I111 -> 0.011 | K111: =J111 -> 0.011 | L111: =K111 -> 0.011 | M111: =L111 -> 0.011
B112: Fees ($) | D112: =IF((D111*D96)<0,0,(D111*D96)) -> 5225 | E112: =IF((E111*E96)<0,0,(E111*E96)) -> 5585.525 | F112: =IF((F111*F96)<0,0,(F111*F96)) -> 5970.9262 | G112: =IF((G111*G96)<0,0,(G111*G96)) -> 6382.9201 | H112: =IF((H111*H96)<0,0,(H111*H96)) -> 6823.3416 | I112: =IF((I111*I96)<0,0,(I111*I96)) -> 7294.1522 | J112: =IF((J111*J96)<0,0,(J111*J96)) -> 7797.4487 | K112: =IF((K111*K96)<0,0,(K111*K96)) -> 8335.4727 | ... M112: =IF((M111*M96)<0,0,(M111*M96)) -> 9525.4531 | AI112: =SUM(D112:N112) -> 71850.86 | AJ112: =AI112/AI114 -> 1
B114: income needed inclusive of fees | D114: =IF(D91<=$C$5,(D108+D112),0) -> 5225 | E114: =IF(E91<=$C$5,(E108+E112),0) -> 5585.525 | F114: =IF(F91<=$C$5,(F108+F112),0) -> 5970.9262 | G114: =IF(G91<=$C$5,(G108+G112),0) -> 6382.9201 | H114: =IF(H91<=$C$5,(H108+H112),0) -> 6823.3416 | I114: =IF(I91<=$C$5,(I108+I112),0) -> 7294.1522 | J114: =IF(J91<=$C$5,(J108+J112),0) -> 7797.4487 | K114: =IF(K91<=$C$5,(K108+K112),0) -> 8335.4727 | ... M114: =IF(M91<=$C$5,(M108+M112),0) -> 9525.4531 | AI114: =SUM(D114:N114) -> 71850.86
B116: Finial Closing balance | D116: =D106-D108 -> 513000 | E116: =E106-E108 -> 548397 | F116: =F106-F108 -> 586236.39 | G116: =G106-G108 -> 626686.7 | H116: =H106-H108 -> 669928.09 | I116: =I106-I108 -> 716153.12 | J116: =J106-J108 -> 765567.69 | K116: =K106-K108 -> 818391.86 | ... M116: =M106-M108 -> 935226.3

Sheet International Holidays
B1: Car for Partner 2
B2: Calander Year at Stage | C2: ='Income - Stage 1'!C3 -> 2026
B3: Start year | C3: ='Income - Stage 1'!C4 -> 1
B4: Stage length | C4: 23
B5: Finish Year | C5: =C2+C4 -> 2049
B6: The year that needs to be iqual to $0 is | C6: =C5+1 -> 2050
B8: Partner 1 age at start of Stage | C8: ='Income - Stage 1'!C7 -> 65
B9: Partner 1 age at END of Stage | C9: =C8+C4 -> 88
B11: Partner 2 age at stage of stage | C11: ='Income - Stage 1'!C8 -> 62
B12: Partner 2 age at END of Stage | C12: =C11+C4 -> 85
B14: Tax Rate (%) | C14: 0.15
B15: Fees % | C15: 0.011
B16: Inflation | C16: 0.03
B18: Portfolio | C18: Balanced | D18: "- this is a pull down menue that automatically fills in the Income % and Growth %"
B19: Portfolio Attributes
B20: income return (%) | C20: 0.035
B21: Growth (%) | C21: 0.045
B23: Calander Year | D23: =C2 -> 2026 | E23: =D23+1 -> 2027 | F23: =E23+1 -> 2028 | G23: =F23+1 -> 2029 | H23: =G23+1 -> 2030 | I23: =H23+1 -> 2031 | J23: =I23+1 -> 2032 | K23: =J23+1 -> 2033 | L23: =K23+1 -> 2034 | ... AI23: =AH23+1 -> 2057
B24: Year | D24: =C3 -> 1 | E24: =D24+1 -> 2 | F24: =E24+1 -> 3 | G24: =F24+1 -> 4 | H24: =G24+1 -> 5 | I24: =H24+1 -> 6 | J24: =I24+1 -> 7 | K24: =J24+1 -> 8 | L24: =K24+1 -> 9 | ... AI24: =AH24+1 -> 32
B25: Partner 1 age | D25: =C8 -> 65 | E25: =D25+1 -> 66 | F25: =E25+1 -> 67 | G25: =F25+1 -> 68 | H25: =G25+1 -> 69 | I25: =H25+1 -> 70 | J25: =I25+1 -> 71 | K25: =J25+1 -> 72 | L25: =K25+1 -> 73 | ... AI25: =AH25+1 -> 96
B26: Partner 2 age | D26: =C11 -> 62 | E26: =D26+1 -> 63 | F26: =E26+1 -> 64 | G26: =F26+1 -> 65 | H26: =G26+1 -> 66 | I26: =H26+1 -> 67 | J26: =I26+1 -> 68 | K26: =J26+1 -> 69 | L26: =K26+1 -> 70 | ... AI26: =AH26+1 -> 93
B29: open balance | D29: 142534.16 | E29: =D56 -> 140238.58 | F29: =E56 -> 137771.42 | G29: =F56 -> 135119.83 | H29: =G56 -> 132270.04 | I29: =H56 -> 129207.23 | J29: =I56 -> 125915.47 | K29: =J56 -> 122377.65 | L29: =K56 -> 118575.38 | ... AI29: =AH56 -> 2.4705645e-10
B30: income return (%) | D30: =C20 -> 0.035 | E30: =D30 -> 0.035 | F30: =E30 -> 0.035 | G30: =F30 -> 0.035 | H30: =G30 -> 0.035 | I30: =H30 -> 0.035 | J30: =I30 -> 0.035 | K30: =J30 -> 0.035 | L30: =K30 -> 0.035 | ... AI30: =AH30 -> 0.035
B31: income return ($) | D31: =D29*D30 -> 4988.6955 | E31: =E29*E30 -> 4908.3505 | F31: =F29*F30 -> 4821.9997 | G31: =G29*G30 -> 4729.1941 | H31: =H29*H30 -> 4629.4514 | I31: =I29*I30 -> 4522.2529 | J31: =J29*J30 -> 4407.0413 | K31: =K29*K30 -> 4283.2176 | ... AI31: =AI29*AI30 -> 8.6469758e-12
B32: Tax Rate (%) | D32: =C14 -> 0.15 | E32: =D32 -> 0.15 | F32: =E32 -> 0.15 | G32: =F32 -> 0.15 | H32: =G32 -> 0.15 | I32: =H32 -> 0.15 | J32: =I32 -> 0.15 | K32: =J32 -> 0.15 | L32: =K32 -> 0.15 | ... AI32: =AH32 -> 0.15
B33: Tax Rate ($) | D33: =IF((D31*D32)<0,0,(D31*D32)) -> 748.30432 | E33: =IF((E31*E32)<0,0,(E31*E32)) -> 736.25257 | F33: =IF((F31*F32)<0,0,(F31*F32)) -> 723.29995 | G33: =IF((G31*G32)<0,0,(G31*G32)) -> 709.37912 | H33: =IF((H31*H32)<0,0,(H31*H32)) -> 694.41771 | I33: =IF((I31*I32)<0,0,(I31*I32)) -> 678.33794 | J33: =IF((J31*J32)<0,0,(J31*J32)) -> 661.0562 | K33: =IF((K31*K32)<0,0,(K31*K32)) -> 642.48265 | ... AI33: =IF((AI31*AI32)<0,0,(AI31*AI32)) -> 1.2970464e-12
B34: Income after tax | D34: =IF((D31-D33)<0,0,(D31-D33)) -> 4240.3912 | E34: =IF((E31-E33)<0,0,(E31-E33)) -> 4172.0979 | F34: =IF((F31-F33)<0,0,(F31-F33)) -> 4098.6997 | G34: =IF((G31-G33)<0,0,(G31-G33)) -> 4019.815 | H34: =IF((H31-H33)<0,0,(H31-H33)) -> 3935.0337 | I34: =IF((I31-I33)<0,0,(I31-I33)) -> 3843.915 | J34: =IF((J31-J33)<0,0,(J31-J33)) -> 3745.9851 | K34: =IF((K31-K33)<0,0,(K31-K33)) -> 3640.735 | ... AI34: =IF((AI31-AI33)<0,0,(AI31-AI33)) -> 7.3499294e-12
B36: Growth (%) | D36: =C21 -> 0.045 | E36: =D36 -> 0.045 | F36: =E36 -> 0.045 | G36: =F36 -> 0.045 | H36: =G36 -> 0.045 | I36: =H36 -> 0.045 | J36: =I36 -> 0.045 | K36: =J36 -> 0.045 | L36: =K36 -> 0.045 | ... AI36: =AH36 -> 0.045
B37: Growth ($) | D37: =IF((D36*D29)<0,0,(D36*D29)) -> 6414.0371 | E37: =IF((E36*E29)<0,0,(E36*E29)) -> 6310.7363 | F37: =IF((F36*F29)<0,0,(F36*F29)) -> 6199.7139 | G37: =IF((G36*G29)<0,0,(G36*G29)) -> 6080.3925 | H37: =IF((H36*H29)<0,0,(H36*H29)) -> 5952.1518 | I37: =IF((I36*I29)<0,0,(I36*I29)) -> 5814.3252 | J37: =IF((J36*J29)<0,0,(J36*J29)) -> 5666.196 | K37: =IF((K36*K29)<0,0,(K36*K29)) -> 5506.9941 | ... AI37: =IF((AI36*AI29)<0,0,(AI36*AI29)) -> 1.111754e-11
B39: Closing Balance | D39: =D29+D34+D37 -> 153188.58 | E39: =E29+E34+E37 -> 150721.42 | F39: =F29+F34+F37 -> 148069.83 | G39: =G29+G34+G37 -> 145220.04 | H39: =H29+H34+H37 -> 142157.23 | I39: =I29+I34+I37 -> 138865.47 | J39: =J29+J34+J37 -> 135327.65 | K39: =K29+K34+K37 -> 131525.38 | ... AI39: =AI29+AI34+AI37 -> 2.6552392e-10
B41: holiday costs
B42: Weeks per year | C42: 3
B43: Days away | C43: =C42*7 -> 21
B45: Accomodation cost per night | C45: 350
B46: Transport cost per day | C46: 150
B47: Food cost per day | C47: 200
B48: Fun cost per day | C48: 200
B49: No of Airfairs | C49: 2
B50: Tickets per person | C50: 3500
B52: Hollding Costs - Total | C52: =(C43*(C45+C46+C47+C48)+(C49*C50)) -> 25900
B53: Frequence of years between trips | C53: 2
B54: Hollding Costs - Total | C54: =C52/C53 -> 12950 | D54: =IF(D23<$C$6,C54,0) -> 12950 | E54: =IF(E23<$C$6,D54,0) -> 12950 | F54: =IF(F23<$C$6,E54,0) -> 12950 | G54: =IF(G23<$C$6,F54,0) -> 12950 | H54: =IF(H23<$C$6,G54,0) -> 12950 | I54: =IF(I23<$C$6,H54,0) -> 12950 | J54: =IF(J23<$C$6,I54,0) -> 12950 | K54: =IF(K23<$C$6,J54,0) -> 12950 | ... AI54: =IF(AI23<$C$6,AH54,0) -> 0
B56: income needed ex fees | D56: =D39-D54 -> 140238.58 | E56: =E39-E54 -> 137771.42 | F56: =F39-F54 -> 135119.83 | G56: =G39-G54 -> 132270.04 | H56: =H39-H54 -> 129207.23 | I56: =I39-I54 -> 125915.47 | J56: =J39-J54 -> 122377.65 | K56: =K39-K54 -> 118575.38 | ... AI56: =AI39-AI54 -> 2.6552392e-10
B57: Inflation assumed | D57: =C16 -> 0.03 | E57: =D57 -> 0.03 | F57: =E57 -> 0.03 | G57: =F57 -> 0.03 | H57: =G57 -> 0.03 | I57: =H57 -> 0.03 | J57: =I57 -> 0.03 | K57: =J57 -> 0.03 | L57: =K57 -> 0.03 | ... AI57: =AH57 -> 0.03
B59: Fees (%) | D59: =C15 -> 0.011 | E59: =D59 -> 0.011 | F59: =E59 -> 0.011 | G59: =F59 -> 0.011 | H59: =G59 -> 0.011 | I59: =H59 -> 0.011 | J59: =I59 -> 0.011 | K59: =J59 -> 0.011 | L59: =K59 -> 0.011 | ... AI59: =AH59 -> 0.011
B60: Fees ($) | D60: =IF((D59*D29)<0,0,(D59*D29)) -> 1567.8757 | E60: =IF((E59*E29)<0,0,(E59*E29)) -> 1542.6244 | F60: =IF((F59*F29)<0,0,(F59*F29)) -> 1515.4856 | G60: =IF((G59*G29)<0,0,(G59*G29)) -> 1486.3182 | H60: =IF((H59*H29)<0,0,(H59*H29)) -> 1454.9704 | I60: =IF((I59*I29)<0,0,(I59*I29)) -> 1421.2795 | J60: =IF((J59*J29)<0,0,(J59*J29)) -> 1385.0701 | K60: =IF((K59*K29)<0,0,(K59*K29)) -> 1346.1541 | ... AI60: =IF((AI59*AI29)<0,0,(AI59*AI29)) -> 2.717621e-12 | AJ60: =AI60/AI62 -> #DIV/0!
B62: income needed inclusive of fees | D62: =IF(D23<=$C$66,(D56+D60),0) -> 0 | E62: =IF(E23<=$C$66,(E56+E60),0) -> 0 | F62: =IF(F23<=$C$66,(F56+F60),0) -> 0 | G62: =IF(G23<=$C$66,(G56+G60),0) -> 0 | H62: =IF(H23<=$C$66,(H56+H60),0) -> 0 | I62: =IF(I23<=$C$66,(I56+I60),0) -> 0 | J62: =IF(J23<=$C$66,(J56+J60),0) -> 0 | K62: =IF(K23<=$C$66,(K56+K60),0) -> 0 | ... AI62: =IF(AI23<=$C$66,(AI56+AI60),0) -> 0
B64: Finial Closing balance | D64: =D39-D56 -> 12950 | E64: =E39-E56 -> 12950 | F64: =F39-F56 -> 12950 | G64: =G39-G56 -> 12950 | H64: =H39-H56 -> 12950 | I64: =I39-I56 -> 12950 | J64: =J39-J56 -> 12950 | K64: =K39-K56 -> 12950 | ... AI64: =AI39-AI56 -> 0
B66: if by | D66: =D23 -> 2026
B67: I need | D67: =D29 -> 142534.16 | E67: in capital
B68: Assuming
B69: Portfolio | D69: Balanced | E69: "- this is a pull down menue that automatically fills in the Income % and Growth %"
B70: Portfolio Attributes
B71: income return (%) | D71: 0.035
B72: Growth (%) | D72: 0.045
B74: Stage 2 Funding at beging of Stage 1
B75: Calander Year at Stage | C75: 2026
B76: Start year | C76: 1
B77: Stage length | C77: 5
B78: Finish Year | C78: =C75+C77 -> 2031
B79: Partner 1 age | C79: 65
B80: Partner 2 age | C80: 62
B81: Tax Rate (%) | C81: 0
B82: Fees % | C82: 0.011
B83: Inflation | C83: 0.03
B85: Portfolio | C85: =C18 -> Balanced | D85: "- this is a pull down menue that automatically fills in the Income % and Growth %"
B86: Portfolio Attributes
B87: income return (%) | C87: =C20 -> 0.035
B88: Growth (%) | C88: =C21 -> 0.045
B90: Calander Year | D90: =C75 -> 2026 | E90: =D90+1 -> 2027 | F90: =E90+1 -> 2028 | G90: =F90+1 -> 2029 | H90: =G90+1 -> 2030 | I90: =H90+1 -> 2031 | J90: =I90+1 -> 2032 | K90: =J90+1 -> 2033 | L90: =K90+1 -> 2034 | M90: =L90+1 -> 2035
B91: Year | D91: 0 | E91: =D91+1 -> 1 | F91: =E91+1 -> 2 | G91: =F91+1 -> 3 | H91: =G91+1 -> 4 | I91: =H91+1 -> 5 | J91: =I91+1 -> 6 | K91: =J91+1 -> 7 | L91: =K91+1 -> 8 | M91: =L91+1 -> 9
B92: Partner 1 age | D92: =C79 -> 65 | E92: =D92+1 -> 66 | F92: =E92+1 -> 67 | G92: =F92+1 -> 68 | H92: =G92+1 -> 69 | I92: =H92+1 -> 70 | J92: =I92+1 -> 71 | K92: =J92+1 -> 72 | L92: =K92+1 -> 73 | M92: =L92+1 -> 74
B93: Partner 2 age | D93: =C80 -> 62 | E93: =D93+1 -> 63 | F93: =E93+1 -> 64 | G93: =F93+1 -> 65 | H93: =G93+1 -> 66 | I93: =H93+1 -> 67 | J93: =I93+1 -> 68 | K93: =J93+1 -> 69 | L93: =K93+1 -> 70 | M93: =L93+1 -> 71
B96: open balance | D96: 475000 | E96: =D106-D114 -> 507775 | F96: =E106-E114 -> 542811.47 | G96: =F106-F114 -> 580265.47 | H96: =G106-G114 -> 620303.78 | I96: =H106-H114 -> 663104.75 | J96: =I106-I114 -> 708858.97 | K96: =J106-J114 -> 757770.24 | L96: =K106-K114 -> 810056.39 | M96: =L106-L114 -> 865950.28
B97: income return (%) | D97: =C87 -> 0.035 | E97: =D97 -> 0.035 | F97: =E97 -> 0.035 | G97: =F97 -> 0.035 | H97: =G97 -> 0.035 | I97: =H97 -> 0.035 | J97: =I97 -> 0.035 | K97: =J97 -> 0.035 | L97: =K97 -> 0.035 | M97: =L97 -> 0.035
B98: income return ($) | D98: =D96*D97 -> 16625 | E98: =E96*E97 -> 17772.125 | F98: =F96*F97 -> 18998.402 | G98: =G96*G97 -> 20309.291 | H98: =H96*H97 -> 21710.632 | I98: =I96*I97 -> 23208.666 | J98: =J96*J97 -> 24810.064 | K98: =K96*K97 -> 26521.958 | ... M98: =M96*M97 -> 30308.26
B99: Tax Rate (%) | D99: =C81 -> 0 | E99: =D99 -> 0 | F99: =E99 -> 0 | G99: =F99 -> 0 | H99: =G99 -> 0 | I99: =H99 -> 0 | J99: =I99 -> 0 | K99: =J99 -> 0 | L99: =K99 -> 0 | M99: =L99 -> 0
B100: Tax Rate ($) | D100: =IF((D98*D99)<0,0,(D98*D99)) -> 0 | E100: =IF((E98*E99)<0,0,(E98*E99)) -> 0 | F100: =IF((F98*F99)<0,0,(F98*F99)) -> 0 | G100: =IF((G98*G99)<0,0,(G98*G99)) -> 0 | H100: =IF((H98*H99)<0,0,(H98*H99)) -> 0 | I100: =IF((I98*I99)<0,0,(I98*I99)) -> 0 | J100: =IF((J98*J99)<0,0,(J98*J99)) -> 0 | K100: =IF((K98*K99)<0,0,(K98*K99)) -> 0 | ... M100: =IF((M98*M99)<0,0,(M98*M99)) -> 0 | AI100: =SUM(D100:N100) -> 0
B101: Income after tax | D101: =IF((D98-D100)<0,0,(D98-D100)) -> 16625 | E101: =IF((E98-E100)<0,0,(E98-E100)) -> 17772.125 | F101: =IF((F98-F100)<0,0,(F98-F100)) -> 18998.402 | G101: =IF((G98-G100)<0,0,(G98-G100)) -> 20309.291 | H101: =IF((H98-H100)<0,0,(H98-H100)) -> 21710.632 | I101: =IF((I98-I100)<0,0,(I98-I100)) -> 23208.666 | J101: =IF((J98-J100)<0,0,(J98-J100)) -> 24810.064 | K101: =IF((K98-K100)<0,0,(K98-K100)) -> 26521.958 | ... M101: =IF((M98-M100)<0,0,(M98-M100)) -> 30308.26 | AI101: =SUM(D101:N101) -> 228616.37
B103: Growth (%) | D103: =C88 -> 0.045 | E103: =D103 -> 0.045 | F103: =E103 -> 0.045 | G103: =F103 -> 0.045 | H103: =G103 -> 0.045 | I103: =H103 -> 0.045 | J103: =I103 -> 0.045 | K103: =J103 -> 0.045 | L103: =K103 -> 0.045 | M103: =L103 -> 0.045
B104: Growth ($) | D104: =IF((D103*D96)<0,0,(D103*D96)) -> 21375 | E104: =IF((E103*E96)<0,0,(E103*E96)) -> 22849.875 | F104: =IF((F103*F96)<0,0,(F103*F96)) -> 24426.516 | G104: =IF((G103*G96)<0,0,(G103*G96)) -> 26111.946 | H104: =IF((H103*H96)<0,0,(H103*H96)) -> 27913.67 | I104: =IF((I103*I96)<0,0,(I103*I96)) -> 29839.714 | J104: =IF((J103*J96)<0,0,(J103*J96)) -> 31898.654 | K104: =IF((K103*K96)<0,0,(K103*K96)) -> 34099.661 | ... M104: =IF((M103*M96)<0,0,(M103*M96)) -> 38967.763 | AI104: =SUM(D104:M104) -> 293935.34
B106: Closing Balance | D106: =D96+D101+D104 -> 513000 | E106: =E96+E101+E104 -> 548397 | F106: =F96+F101+F104 -> 586236.39 | G106: =G96+G101+G104 -> 626686.7 | H106: =H96+H101+H104 -> 669928.09 | I106: =I96+I101+I104 -> 716153.12 | J106: =J96+J101+J104 -> 765567.69 | K106: =K96+K101+K104 -> 818391.86 | ... M106: =M96+M101+M104 -> 935226.3
B108: income needed ex fees | D108: 0 | E108: =D108*(1+D109) -> 0 | F108: =E108*(1+E109) -> 0 | G108: =F108*(1+F109) -> 0 | H108: =G108*(1+G109) -> 0 | I108: =H108*(1+H109) -> 0 | J108: =I108*(1+I109) -> 0 | K108: =J108*(1+J109) -> 0 | L108: =K108*(1+K109) -> 0 | M108: =L108*(1+L109) -> 0
B109: Inflation assumed | D109: =C83 -> 0.03 | E109: =D109 -> 0.03 | F109: =E109 -> 0.03 | G109: =F109 -> 0.03 | H109: =G109 -> 0.03 | I109: =H109 -> 0.03 | J109: =I109 -> 0.03 | K109: =J109 -> 0.03 | L109: =K109 -> 0.03 | M109: =L109 -> 0.03
B111: Fees (%) | D111: =C82 -> 0.011 | E111: =D111 -> 0.011 | F111: =E111 -> 0.011 | G111: =F111 -> 0.011 | H111: =G111 -> 0.011 | I111: =H111 -> 0.011 | J111: =I111 -> 0.011 | K111: =J111 -> 0.011 | L111: =K111 -> 0.011 | M111: =L111 -> 0.011
B112: Fees ($) | D112: =IF((D111*D96)<0,0,(D111*D96)) -> 5225 | E112: =IF((E111*E96)<0,0,(E111*E96)) -> 5585.525 | F112: =IF((F111*F96)<0,0,(F111*F96)) -> 5970.9262 | G112: =IF((G111*G96)<0,0,(G111*G96)) -> 6382.9201 | H112: =IF((H111*H96)<0,0,(H111*H96)) -> 6823.3416 | I112: =IF((I111*I96)<0,0,(I111*I96)) -> 7294.1522 | J112: =IF((J111*J96)<0,0,(J111*J96)) -> 7797.4487 | K112: =IF((K111*K96)<0,0,(K111*K96)) -> 8335.4727 | ... M112: =IF((M111*M96)<0,0,(M111*M96)) -> 9525.4531 | AI112: =SUM(D112:N112) -> 71850.86 | AJ112: =AI112/AI114 -> 1
B114: income needed inclusive of fees | D114: =IF(D91<=$C$5,(D108+D112),0) -> 5225 | E114: =IF(E91<=$C$5,(E108+E112),0) -> 5585.525 | F114: =IF(F91<=$C$5,(F108+F112),0) -> 5970.9262 | G114: =IF(G91<=$C$5,(G108+G112),0) -> 6382.9201 | H114: =IF(H91<=$C$5,(H108+H112),0) -> 6823.3416 | I114: =IF(I91<=$C$5,(I108+I112),0) -> 7294.1522 | J114: =IF(J91<=$C$5,(J108+J112),0) -> 7797.4487 | K114: =IF(K91<=$C$5,(K108+K112),0) -> 8335.4727 | ... M114: =IF(M91<=$C$5,(M108+M112),0) -> 9525.4531 | AI114: =SUM(D114:N114) -> 71850.86
B116: Finial Closing balance | D116: =D106-D108 -> 513000 | E116: =E106-E108 -> 548397 | F116: =F106-F108 -> 586236.39 | G116: =G106-G108 -> 626686.7 | H116: =H106-H108 -> 669928.09 | I116: =I106-I108 -> 716153.12 | J116: =J106-J108 -> 765567.69 | K116: =K106-K108 -> 818391.86 | ... M116: =M106-M108 -> 935226.3

Sheet Travel to see Parents overseas

Sheet Travel to see others

Sheet Medical Expenses
